Workbook

Sheet Dashboard
B2: DASHBOARD — VISÃO GERAL DO CONFINAMENTO BG
B4: REBANHO | E4: ECONÔMICO / NUTRIÇÃO
B5: Total de animais | C5: =COUNTA(Cadastro_Animais!$B$3:$B$5001) -> 385 | E5: Preço da arroba (R$/@) | F5: =Parâmetros!$C$5 -> 310
B6: Touros Bonsmara | C6: =COUNTIF(Cadastro_Animais!$C$3:$C$5001,"Touro Bonsmara") -> 84 | E6: Valor do rebanho (R$) | F6: =SUM(Cadastro_Animais!$O$3:$O$5001) -> 1471372.2
B7: Touros Nelore | C7: =COUNTIF(Cadastro_Animais!$C$3:$C$5001,"Touro Nelore") -> 29 | E7: Custo dieta médio (R$/kg MN) | F7: =Parâmetros!$C$6 -> 0.54970799
B8: Bezerros | C8: =COUNTIF(Cadastro_Animais!$C$3:$C$5001,"Bezerro") -> 165 | E8: Consumo planejado/dia (kg MN) | F8: =Calculadora_Trato!$I$14 -> 3223.944
B9: Novilhas Nelore | C9: =COUNTIF(Cadastro_Animais!$C$3:$C$5001,"Novilha Nelore") -> 70 | E9: Custo total ração/dia (R$) | F9: =Calculadora_Trato!$N$14 -> 1772.2278
B10: Bonsmara Descarte | C10: =COUNTIF(Cadastro_Animais!$C$3:$C$5001,"Touro Bonsmara Descarte") -> 37 | E10: Custo ração/cab/dia (R$) | F10: =IFERROR(Calculadora_Trato!$N$14/COUNTA(Cadastro_Animais!$B$3:$B$5001),"") -> 4.603189
B11: Peso vivo total atual (kg) | C11: =SUM(Cadastro_Animais!$I$3:$I$5001) -> 134331 | E11: @ totais em estoque | F11: =SUM(Cadastro_Animais!$M$3:$M$5001) -> 4746.362
B13: DESEMPENHO (onde há 2+ pesagens) | E13: CUSTO ACUMULADO / @
B14: GMD médio do rebanho (kg/dia) | C14: =IFERROR(AVERAGE(Cadastro_Animais!$L$3:$L$5001),"") -> 2.369628 | E14: Custo nutrição estim. acum. (R$) | F14: =Custo_Nutricao_Lote!$I$12 -> 64360.099
B15: Ganho total acumulado (kg) | C15: =SUM(Cadastro_Animais!$K$3:$K$5001) -> 5995 | E15: Custo nutrição real acum. (R$) | F15: =Custo_Nutricao_Lote!$J$12 -> 101992
B16: @ produzidas (ganho) | C16: =SUM(Cadastro_Animais!$N$3:$N$5001) -> 211.82333 | E16: Custo estim./@ produzida (R$) | F16: =IF(Custo_Nutricao_Lote!$L$12<=0,"",Custo_Nutricao_Lote!$I$12/Custo_Nutricao_Lote!$L$12) -> 303.83857
B17: GMD meta (kg/dia) | C17: =Parâmetros!$C$10 -> 1.4 | E17: Obs.: consumo/custo de ração vêm da Calculadora (planejado). Lance o Trato_Diario para o custo real.

Sheet Venda_Nelore
B2: VENDA — TOUROS NELORE (curral 4-TN)
B3: Frigorífico | C3: PRIMA FOODS S.A. — Araguari/MG
B4: Nota Fiscal / Pedido | C4: NF 78727 · PR/01-239058-01
B5: Data do abate | C5: 46247
B6: Data saída da fazenda | C6: 46246
B8: DADOS DA VENDA
B9: Cabeças | C9: 29
B10: Preço da arroba (R$/@) | C10: 330
B11: Peso de carcaça total (kg) | C11: 8819.5
B12: Arrobas de carcaça (@) | C12: 587.97
B13: Carcaça média por cabeça (kg) | C13: 304.12
B14: Rendimento de carcaça (carcaça ÷ peso fazenda) | C14: 0.5443
B15: Valor bruto | C15: 194029
B16: (−) SENAR | C16: 388.06
B17: VALOR LÍQUIDO | C17: 193640.94
B18: Preço médio por cabeça (líquido) | C18: 6677.27
B19: Pagamento | C19: 32 dias — vencimento 14/09/2026
B20: Dentição | C20: 10× 0 dente · 15× 2 dentes · 4× 4 dentes
B22: CUSTO DO LOTE
B23: Custo de entrada (13.462 kg × 50% ÷ 15 × R$310/@) | C23: 139107.33
B24: Custo de ração (real — Trato_Diário) | C24: 20138.4
B25: Custo fixo (R$2,50/cab/dia × 1.217 cab-dias) | C25: 3042.5
B26: CUSTO TOTAL | C26: 162288.24
B27: Custo total por cabeça | C27: 5596.15
B29: RESULTADO
B30: Receita líquida | C30: 193640.94
B31: (−) Custo total | C31: 162288.24
B32: LUCRO DO LOTE | C32: 31352.7
B33: Lucro por cabeça | C33: 1081.13
B34: Margem sobre a receita | C34: 0.162
B35: ROI sobre o custo | C35: 0.193
B36: Custo da arroba produzida (ração+fixo) | C36: 166.49
B38: ZOOTÉCNICO
B39: Peso médio de entrada (kg) | C39: 464.2
B40: Peso médio de saída (kg) | C40: 558.7
B41: Ganho total do lote (kg) | C41: 2741
B42: GMD médio (kg/dia) | C42: 2.26
B43: Dias de confinamento (média) | C43: 43

Sheet Parâmetros
B2: PARÂMETROS (edite as células amarelas)
B3: Parâmetro | C3: Valor | D3: Observação
B4: Data de referência | C4: 46246 | D4: Data usada para calcular os dias de confinamento.
B5: Preço da arroba (R$/@) | C5: 310 | D5: PLACEHOLDER — ajuste ao preço da arroba do boi gordo que você usa.
B6: Custo da ração (R$/kg matéria natural) | C6: =IFERROR(Calculadora_Trato!$N$14/Calculadora_Trato!$I$14,"") -> 0.54970799 | D6: Automático: custo médio ponderado das dietas (Calculadora_Trato). Cada curral usa sua própria dieta.
B7: % Matéria seca da dieta | C7: 0.55 | D7: PLACEHOLDER — teor de MS da dieta (ex.: 55%). Usado para converter MN em MS.
B8: Rendimento de carcaça (%) | C8: 0.53 | D8: PLACEHOLDER — rendimento de carcaça para converter peso vivo em @.
B9: Custo fixo diário (R$/cab/dia) | C9: 2.5 | D9: PLACEHOLDER — sanidade + mão de obra + demais custos por cabeça/dia (fora ração).
B10: GMD meta (kg/dia) | C10: 1.4 | D10: Meta de ganho médio diário para comparação.
B11: Peso de abate alvo (kg) | C11: 500 | D11: Peso vivo alvo para projeções.

Sheet Precos_Insumos
A1: COMPRAS / PREÇOS DE INSUMOS (por data)
A2: Registre CADA compra: Data, Insumo, Preço R$/kg e Qtd. O custo das dietas usa sempre o preço da compra mais recente de cada insumo.
A3: Data | B3: Insumo | C3: Preço (R$/kg) | D3: Qtd Comprada (kg) | E3: Valor Total (R$) | F3: Fornecedor | G3: Obs
A4: 46202 | B4: Silagem de Capim | C4: 0.1 | E4: =IF(D4="","",C4*D4)
A5: 46202 | B5: Promill | C5: 1.1 | E5: =IF(D5="","",C5*D5)
A6: 46202 | B6: Milho Moído | C6: 1.13 | E6: =IF(D6="","",C6*D6)
A7: 46202 | B7: Ureia | C7: 3.8 | E7: =IF(D7="","",C7*D7)
A8: 46202 | B8: Núcleo Flex (Flexbeef MD) | C8: 3.8 | E8: =IF(D8="","",C8*D8)
E9: =IF(D9="","",C9*D9)
E10: =IF(D10="","",C10*D10)
E11: =IF(D11="","",C11*D11)
E12: =IF(D12="","",C12*D12)
E13: =IF(D13="","",C13*D13)
E14: =IF(D14="","",C14*D14)
E15: =IF(D15="","",C15*D15)
E16: =IF(D16="","",C16*D16)
E17: =IF(D17="","",C17*D17)
E18: =IF(D18="","",C18*D18)
E19: =IF(D19="","",C19*D19)
E20: =IF(D20="","",C20*D20)
... E203: =IF(D203="","",C203*D203)

Sheet Estoque_Insumos
B2: ESTOQUE DE INSUMOS (estimativa) — BG
B3: Informe o Estoque na data-base e a Data-base de cada insumo (amarelo). O consumo vem dos lançamentos do Trato_Diario, considerando a dieta de cada curral. Consumo/dia = consumo planejado atual (Calculadora).
B5: Insumo | C5: Estoque na data-base (kg) | D5: Data-base | E5: Compras após (kg) | F5: Consumo após (kg) | G5: Estoque Atual (kg) | H5: Consumo/dia atual (kg) | I5: Dias de estoque
B6: Silagem de Capim | E6: =IF($D6="","",SUMIFS(Precos_Insumos!$D$4:$D$203,Precos_Insumos!$B$4:$B$203,$B6,Precos_Insumos!$A$4:$A$203,">"&$D6)) | F6: =IF($D6="","",SUMPRODUCT(SUMIFS(Trato_Diario!$F$4:$F$203,Trato_Diario!$B$4:$B$203,Currais!$A$3:$A$8,Trato_Diario!$A$4:$A$203,">="&$D6),Currais!$L$3:$L$8)) | G6: =IF($C6="","",$C6+N(E6)-N(F6)) | H6: =SUMPRODUCT(Calculadora_Trato!$I$8:$I$13,Currais!$L$3:$L$8) -> 1913.057 | I6: =IF(OR(G6="",H6=0),"",G6/H6)
B7: Promill | E7: =IF($D7="","",SUMIFS(Precos_Insumos!$D$4:$D$203,Precos_Insumos!$B$4:$B$203,$B7,Precos_Insumos!$A$4:$A$203,">"&$D7)) | F7: =IF($D7="","",SUMPRODUCT(SUMIFS(Trato_Diario!$F$4:$F$203,Trato_Diario!$B$4:$B$203,Currais!$A$3:$A$8,Trato_Diario!$A$4:$A$203,">="&$D7),Currais!$M$3:$M$8)) | G7: =IF($C7="","",$C7+N(E7)-N(F7)) | H7: =SUMPRODUCT(Calculadora_Trato!$I$8:$I$13,Currais!$M$3:$M$8) -> 791.34672 | I7: =IF(OR(G7="",H7=0),"",G7/H7)
B8: Milho Moído | E8: =IF($D8="","",SUMIFS(Precos_Insumos!$D$4:$D$203,Precos_Insumos!$B$4:$B$203,$B8,Precos_Insumos!$A$4:$A$203,">"&$D8)) | F8: =IF($D8="","",SUMPRODUCT(SUMIFS(Trato_Diario!$F$4:$F$203,Trato_Diario!$B$4:$B$203,Currais!$A$3:$A$8,Trato_Diario!$A$4:$A$203,">="&$D8),Currais!$N$3:$N$8)) | G8: =IF($C8="","",$C8+N(E8)-N(F8)) | H8: =SUMPRODUCT(Calculadora_Trato!$I$8:$I$13,Currais!$N$3:$N$8) -> 473.33791 | I8: =IF(OR(G8="",H8=0),"",G8/H8)
B9: Ureia | E9: =IF($D9="","",SUMIFS(Precos_Insumos!$D$4:$D$203,Precos_Insumos!$B$4:$B$203,$B9,Precos_Insumos!$A$4:$A$203,">"&$D9)) | F9: =IF($D9="","",SUMPRODUCT(SUMIFS(Trato_Diario!$F$4:$F$203,Trato_Diario!$B$4:$B$203,Currais!$A$3:$A$8,Trato_Diario!$A$4:$A$203,">="&$D9),Currais!$O$3:$O$8)) | G9: =IF($C9="","",$C9+N(E9)-N(F9)) | H9: =SUMPRODUCT(Calculadora_Trato!$I$8:$I$13,Currais!$O$3:$O$8) -> 16.11972 | I9: =IF(OR(G9="",H9=0),"",G9/H9)
B10: Núcleo Flex (Flexbeef MD) | E10: =IF($D10="","",SUMIFS(Precos_Insumos!$D$4:$D$203,Precos_Insumos!$B$4:$B$203,$B10,Precos_Insumos!$A$4:$A$203,">"&$D10)) | F10: =IF($D10="","",SUMPRODUCT(SUMIFS(Trato_Diario!$F$4:$F$203,Trato_Diario!$B$4:$B$203,Currais!$A$3:$A$8,Trato_Diario!$A$4:$A$203,">="&$D10),Currais!$P$3:$P$8)) | G10: =IF($C10="","",$C10+N(E10)-N(F10)) | H10: =SUMPRODUCT(Calculadora_Trato!$I$8:$I$13,Currais!$P$3:$P$8) -> 30.082608 | I10: =IF(OR(G10="",H10=0),"",G10/H10)
B12: Obs.: preencha o estoque e a data-base de cada insumo. O 'Consumo/dia atual' já aparece (consumo planejado da Calculadora × % da dieta de cada curral). 'Dias de estoque' = estoque ÷ consumo/dia.

Sheet Ingredientes_Dieta
B2: INGREDIENTES E DIETAS — BARRA GRANDE
B3: Preço vem AUTOMÁTICO da última compra (Precos_Insumos). Edite as % de inclusão (amarelo) de cada dieta. Valores nas colunas Touros/Boi Nelore/Bezerros/Descarte = % de inclusão.
B5: Ingrediente | C5: Preço (R$/kg) | D5: Última compra | E5: Touros | F5: Boi Nelore | G5: Bezerros | H5: Descarte
B6: Silagem de Capim | C6: =IFERROR(AVERAGEIFS(Precos_Insumos!$C$4:$C$203,Precos_Insumos!$B$4:$B$203,B6,Precos_Insumos!$A$4:$A$203,D6),0) -> 0.1 | D6: =IFERROR(_xlfn.MAXIFS(Precos_Insumos!$A$4:$A$203,Precos_Insumos!$B$4:$B$203,B6),"") -> 46202 | E6: 0.68 | F6: 0.48 | G6: 0.62 | H6: 0.57
B7: Promill | C7: =IFERROR(AVERAGEIFS(Precos_Insumos!$C$4:$C$203,Precos_Insumos!$B$4:$B$203,B7,Precos_Insumos!$A$4:$A$203,D7),0) -> 1.1 | D7: =IFERROR(_xlfn.MAXIFS(Precos_Insumos!$A$4:$A$203,Precos_Insumos!$B$4:$B$203,B7),"") -> 46202 | E7: 0.22 | F7: 0.22 | G7: 0.3 | H7: 0.26
B8: Milho Moído | C8: =IFERROR(AVERAGEIFS(Precos_Insumos!$C$4:$C$203,Precos_Insumos!$B$4:$B$203,B8,Precos_Insumos!$A$4:$A$203,D8),0) -> 1.13 | D8: =IFERROR(_xlfn.MAXIFS(Precos_Insumos!$A$4:$A$203,Precos_Insumos!$B$4:$B$203,B8),"") -> 46202 | E8: 0.087 | F8: 0.285 | G8: 0.065 | H8: 0.155
B9: Ureia | C9: =IFERROR(AVERAGEIFS(Precos_Insumos!$C$4:$C$203,Precos_Insumos!$B$4:$B$203,B9,Precos_Insumos!$A$4:$A$203,D9),0) -> 3.8 | D9: =IFERROR(_xlfn.MAXIFS(Precos_Insumos!$A$4:$A$203,Precos_Insumos!$B$4:$B$203,B9),"") -> 46202 | E9: 0.005 | F9: 0.005 | G9: 0.005 | H9: 0.005
B10: Núcleo Flex (Flexbeef MD) | C10: =IFERROR(AVERAGEIFS(Precos_Insumos!$C$4:$C$203,Precos_Insumos!$B$4:$B$203,B10,Precos_Insumos!$A$4:$A$203,D10),0) -> 3.8 | D10: =IFERROR(_xlfn.MAXIFS(Precos_Insumos!$A$4:$A$203,Precos_Insumos!$B$4:$B$203,B10),"") -> 46202 | E10: 0.008 | F10: 0.01 | G10: 0.01 | H10: 0.01
B11: Custo da dieta (R$/kg) | E11: =SUMPRODUCT($C$6:$C$10,E6:E10) -> 0.45771 | F11: =SUMPRODUCT($C$6:$C$10,F6:F10) -> 0.66905 | G11: =SUMPRODUCT($C$6:$C$10,G6:G10) -> 0.52245 | H11: =SUMPRODUCT($C$6:$C$10,H6:H10) -> 0.57515
B13: Conferência % (cada dieta deve dar 100%): | E13: =SUM(E6:E10) -> 1 | F13: =SUM(F6:F10) -> 1 | G13: =SUM(G6:G10) -> 1 | H13: =SUM(H6:H10) -> 1

Sheet Calculadora_Trato
B2: CALCULADORA DE TRATO POR CURRAL — BG
B3: Base = Nº cabeças × Peso médio × % do peso vivo (MN). Ajuste a % do peso vivo e o Ajuste % de cada curral (amarelo). Cada curral usa sua dieta (Currais). Split manhã/almoço/tarde editável.
B5: % do peso vivo (MN): | D5: 0.024 | E5: Manhã | F5: 0.4 | G5: Almoço | H5: 0.2 | I5: Tarde | J5: 0.4
B7: Curral | C7: Nº Cab | D7: Peso Médio (kg) | E7: Dieta | F7: Custo Dieta (R$/kg) | G7: Base Total (kg MN/dia) | H7: Ajuste % | I7: Consumo Ajustado (kg MN/dia) | J7: kg MN/cab | K7: Trato Manhã (kg) | L7: Trato Almoço (kg) | M7: Trato Tarde (kg) | N7: Custo Planejado/dia (R$) | O7: Custo/cab/dia (R$)
B8: 2 | C8: =IFERROR(INDEX(Currais!$C$3:$C$8,MATCH(B8,Currais!$A$3:$A$8,0)),0) -> 38 | D8: =IFERROR(INDEX(Currais!$E$3:$E$8,MATCH(B8,Currais!$A$3:$A$8,0)),0) -> 551.84211 | E8: =IFERROR(INDEX(Currais!$J$3:$J$8,MATCH(B8,Currais!$A$3:$A$8,0)),"") -> Touros | F8: =IFERROR(INDEX(Currais!$K$3:$K$8,MATCH(B8,Currais!$A$3:$A$8,0)),0) -> 0.45771 | G8: =C8*D8*$D$5 -> 503.28 | H8: 0 | I8: =G8*(1+H8) -> 503.28 | J8: =IF(C8=0,"",I8/C8) -> 13.244211 | K8: =I8*$F$5 -> 201.312 | L8: =I8*$H$5 -> 100.656 | M8: =I8*$J$5 -> 201.312 | N8: =I8*F8 -> 230.35629 | O8: =IF(C8=0,"",N8/C8) -> 6.0620076
B9: 3 | C9: =IFERROR(INDEX(Currais!$C$3:$C$8,MATCH(B9,Currais!$A$3:$A$8,0)),0) -> 46 | D9: =IFERROR(INDEX(Currais!$E$3:$E$8,MATCH(B9,Currais!$A$3:$A$8,0)),0) -> 520.95652 | E9: =IFERROR(INDEX(Currais!$J$3:$J$8,MATCH(B9,Currais!$A$3:$A$8,0)),"") -> Touros | F9: =IFERROR(INDEX(Currais!$K$3:$K$8,MATCH(B9,Currais!$A$3:$A$8,0)),0) -> 0.45771 | G9: =C9*D9*$D$5 -> 575.136 | H9: 0 | I9: =G9*(1+H9) -> 575.136 | J9: =IF(C9=0,"",I9/C9) -> 12.502957 | K9: =I9*$F$5 -> 230.0544 | L9: =I9*$H$5 -> 115.0272 | M9: =I9*$J$5 -> 230.0544 | N9: =I9*F9 -> 263.2455 | O9: =IF(C9=0,"",N9/C9) -> 5.7227282
B10: 4 | C10: =IFERROR(INDEX(Currais!$C$3:$C$8,MATCH(B10,Currais!$A$3:$A$8,0)),0) -> 165 | D10: =IFERROR(INDEX(Currais!$E$3:$E$8,MATCH(B10,Currais!$A$3:$A$8,0)),0) -> 219.67879 | E10: =IFERROR(INDEX(Currais!$J$3:$J$8,MATCH(B10,Currais!$A$3:$A$8,0)),"") -> Bezerros | F10: =IFERROR(INDEX(Currais!$K$3:$K$8,MATCH(B10,Currais!$A$3:$A$8,0)),0) -> 0.52245 | G10: =C10*D10*$D$5 -> 869.928 | H10: 0 | I10: =G10*(1+H10) -> 869.928 | J10: =IF(C10=0,"",I10/C10) -> 5.2722909 | K10: =I10*$F$5 -> 347.9712 | L10: =I10*$H$5 -> 173.9856 | M10: =I10*$J$5 -> 347.9712 | N10: =I10*F10 -> 454.49388 | O10: =IF(C10=0,"",N10/C10) -> 2.7545084
B11: 4-TN | C11: =IFERROR(INDEX(Currais!$C$3:$C$8,MATCH(B11,Currais!$A$3:$A$8,0)),0) -> 29 | D11: =IFERROR(INDEX(Currais!$E$3:$E$8,MATCH(B11,Currais!$A$3:$A$8,0)),0) -> 558.72414 | E11: =IFERROR(INDEX(Currais!$J$3:$J$8,MATCH(B11,Currais!$A$3:$A$8,0)),"") -> Boi Nelore | F11: =IFERROR(INDEX(Currais!$K$3:$K$8,MATCH(B11,Currais!$A$3:$A$8,0)),0) -> 0.66905 | G11: =C11*D11*$D$5 -> 388.872 | H11: 0 | I11: =G11*(1+H11) -> 388.872 | J11: =IF(C11=0,"",I11/C11) -> 13.409379 | K11: =I11*$F$5 -> 155.5488 | L11: =I11*$H$5 -> 77.7744 | M11: =I11*$J$5 -> 155.5488 | N11: =I11*F11 -> 260.17481 | O11: =IF(C11=0,"",N11/C11) -> 8.9715452
B12: (a definir) | C12: =IFERROR(INDEX(Currais!$C$3:$C$8,MATCH(B12,Currais!$A$3:$A$8,0)),0) -> 70 | D12: =IFERROR(INDEX(Currais!$E$3:$E$8,MATCH(B12,Currais!$A$3:$A$8,0)),0) -> 342.02857 | E12: =IFERROR(INDEX(Currais!$J$3:$J$8,MATCH(B12,Currais!$A$3:$A$8,0)),"") -> Boi Nelore | F12: =IFERROR(INDEX(Currais!$K$3:$K$8,MATCH(B12,Currais!$A$3:$A$8,0)),0) -> 0.66905 | G12: =C12*D12*$D$5 -> 574.608 | H12: 0 | I12: =G12*(1+H12) -> 574.608 | J12: =IF(C12=0,"",I12/C12) -> 8.2086857 | K12: =I12*$F$5 -> 229.8432 | L12: =I12*$H$5 -> 114.9216 | M12: =I12*$J$5 -> 229.8432 | N12: =I12*F12 -> 384.44148 | O12: =IF(C12=0,"",N12/C12) -> 5.4920212
B13: 5 | C13: =IFERROR(INDEX(Currais!$C$3:$C$8,MATCH(B13,Currais!$A$3:$A$8,0)),0) -> 37 | D13: =IFERROR(INDEX(Currais!$E$3:$E$8,MATCH(B13,Currais!$A$3:$A$8,0)),0) -> 351.48649 | E13: =IFERROR(INDEX(Currais!$J$3:$J$8,MATCH(B13,Currais!$A$3:$A$8,0)),"") -> Descarte | F13: =IFERROR(INDEX(Currais!$K$3:$K$8,MATCH(B13,Currais!$A$3:$A$8,0)),0) -> 0.57515 | G13: =C13*D13*$D$5 -> 312.12 | H13: 0 | I13: =G13*(1+H13) -> 312.12 | J13: =IF(C13=0,"",I13/C13) -> 8.4356757 | K13: =I13*$F$5 -> 124.848 | L13: =I13*$H$5 -> 62.424 | M13: =I13*$J$5 -> 124.848 | N13: =I13*F13 -> 179.51582 | O13: =IF(C13=0,"",N13/C13) -> 4.8517789
B14: TOTAL | C14: =SUM(C8:C13) -> 385 | G14: =SUM(G8:G13) -> 3223.944 | I14: =SUM(I8:I13) -> 3223.944 | K14: =SUM(K8:K13) -> 1289.5776 | L14: =SUM(L8:L13) -> 644.7888 | M14: =SUM(M8:M13) -> 1289.5776 | N14: =SUM(N8:N13) -> 1772.2278 | O14: =IF(C14=0,"",N14/C14) -> 4.603189

Sheet Trato_Diario
A1: LANÇAMENTO DIÁRIO DE TRATO (REAL) POR CURRAL
A2: Lance o que foi realmente fornecido por dia/curral (amarelo). O custo usa a dieta do curral (Currais). Alimenta o Custo Real por lote e o Estoque.
A3: Data | B3: Curral | C3: Trato Manhã (kg MN) | D3: Trato Almoço (kg MN) | E3: Trato Tarde (kg MN) | F3: Total Dia (kg MN) | G3: Nº Cab | H3: kg MN/cab | I3: Custo Dieta (R$/kg) | J3: Custo Total (R$) | K3: Obs
A4: 46203 | B4: 2 | C4: 320 | D4: 160 | E4: 320 | F4: =IF(AND(C4="",D4="",E4=""),"",N(C4)+N(D4)+N(E4)) -> 800 | G4: =IF(B4="","",IFERROR(INDEX(Currais!$C$3:$C$8,MATCH(B4,Currais!$A$3:$A$8,0)),"")) -> 38 | H4: =IF(OR(F4="",G4="",G4=0),"",F4/G4) -> 21.052632 | I4: =IF(F4="","",IFERROR(INDEX(Currais!$K$3:$K$8,MATCH(B4,Currais!$A$3:$A$8,0)),0)) -> 0.45771 | J4: =IF(F4="","",F4*I4) -> 366.168 | K4: Estimado — rampa
A5: 46204 | B5: 2 | C5: 320 | D5: 160 | E5: 320 | F5: =IF(AND(C5="",D5="",E5=""),"",N(C5)+N(D5)+N(E5)) -> 800 | G5: =IF(B5="","",IFERROR(INDEX(Currais!$C$3:$C$8,MATCH(B5,Currais!$A$3:$A$8,0)),"")) -> 38 | H5: =IF(OR(F5="",G5="",G5=0),"",F5/G5) -> 21.052632 | I5: =IF(F5="","",IFERROR(INDEX(Currais!$K$3:$K$8,MATCH(B5,Currais!$A$3:$A$8,0)),0)) -> 0.45771 | J5: =IF(F5="","",F5*I5) -> 366.168 | K5: Estimado — rampa
A6: 46205 | B6: 2 | C6: 320 | D6: 160 | E6: 320 | F6: =IF(AND(C6="",D6="",E6=""),"",N(C6)+N(D6)+N(E6)) -> 800 | G6: =IF(B6="","",IFERROR(INDEX(Currais!$C$3:$C$8,MATCH(B6,Currais!$A$3:$A$8,0)),"")) -> 38 | H6: =IF(OR(F6="",G6="",G6=0),"",F6/G6) -> 21.052632 | I6: =IF(F6="","",IFERROR(INDEX(Currais!$K$3:$K$8,MATCH(B6,Currais!$A$3:$A$8,0)),0)) -> 0.45771 | J6: =IF(F6="","",F6*I6) -> 366.168 | K6: Estimado — rampa
A7: 46206 | B7: 2 | C7: 360 | D7: 180 | E7: 360 | F7: =IF(AND(C7="",D7="",E7=""),"",N(C7)+N(D7)+N(E7)) -> 900 | G7: =IF(B7="","",IFERROR(INDEX(Currais!$C$3:$C$8,MATCH(B7,Currais!$A$3:$A$8,0)),"")) -> 38 | H7: =IF(OR(F7="",G7="",G7=0),"",F7/G7) -> 23.684211 | I7: =IF(F7="","",IFERROR(INDEX(Currais!$K$3:$K$8,MATCH(B7,Currais!$A$3:$A$8,0)),0)) -> 0.45771 | J7: =IF(F7="","",F7*I7) -> 411.939 | K7: Estimado — rampa
A8: 46207 | B8: 2 | C8: 360 | D8: 180 | E8: 360 | F8: =IF(AND(C8="",D8="",E8=""),"",N(C8)+N(D8)+N(E8)) -> 900 | G8: =IF(B8="","",IFERROR(INDEX(Currais!$C$3:$C$8,MATCH(B8,Currais!$A$3:$A$8,0)),"")) -> 38 | H8: =IF(OR(F8="",G8="",G8=0),"",F8/G8) -> 23.684211 | I8: =IF(F8="","",IFERROR(INDEX(Currais!$K$3:$K$8,MATCH(B8,Currais!$A$3:$A$8,0)),0)) -> 0.45771 | J8: =IF(F8="","",F8*I8) -> 411.939 | K8: Estimado — rampa
A9: 46208 | B9: 2 | C9: 360 | D9: 180 | E9: 360 | F9: =IF(AND(C9="",D9="",E9=""),"",N(C9)+N(D9)+N(E9)) -> 900 | G9: =IF(B9="","",IFERROR(INDEX(Currais!$C$3:$C$8,MATCH(B9,Currais!$A$3:$A$8,0)),"")) -> 38 | H9: =IF(OR(F9="",G9="",G9=0),"",F9/G9) -> 23.684211 | I9: =IF(F9="","",IFERROR(INDEX(Currais!$K$3:$K$8,MATCH(B9,Currais!$A$3:$A$8,0)),0)) -> 0.45771 | J9: =IF(F9="","",F9*I9) -> 411.939 | K9: Estimado — rampa
A10: 46209 | B10: 2 | C10: 400 | D10: 200 | E10: 400 | F10: =IF(AND(C10="",D10="",E10=""),"",N(C10)+N(D10)+N(E10)) -> 1000 | G10: =IF(B10="","",IFERROR(INDEX(Currais!$C$3:$C$8,MATCH(B10,Currais!$A$3:$A$8,0)),"")) -> 38 | H10: =IF(OR(F10="",G10="",G10=0),"",F10/G10) -> 26.315789 | I10: =IF(F10="","",IFERROR(INDEX(Currais!$K$3:$K$8,MATCH(B10,Currais!$A$3:$A$8,0)),0)) -> 0.45771 | J10: =IF(F10="","",F10*I10) -> 457.71 | K10: Estimado — rampa
A11: 46210 | B11: 2 | C11: 400 | D11: 200 | E11: 400 | F11: =IF(AND(C11="",D11="",E11=""),"",N(C11)+N(D11)+N(E11)) -> 1000 | G11: =IF(B11="","",IFERROR(INDEX(Currais!$C$3:$C$8,MATCH(B11,Currais!$A$3:$A$8,0)),"")) -> 38 | H11: =IF(OR(F11="",G11="",G11=0),"",F11/G11) -> 26.315789 | I11: =IF(F11="","",IFERROR(INDEX(Currais!$K$3:$K$8,MATCH(B11,Currais!$A$3:$A$8,0)),0)) -> 0.45771 | J11: =IF(F11="","",F11*I11) -> 457.71 | K11: Estimado — rampa
A12: 46211 | B12: 2 | C12: 400 | D12: 200 | E12: 400 | F12: =IF(AND(C12="",D12="",E12=""),"",N(C12)+N(D12)+N(E12)) -> 1000 | G12: =IF(B12="","",IFERROR(INDEX(Currais!$C$3:$C$8,MATCH(B12,Currais!$A$3:$A$8,0)),"")) -> 38 | H12: =IF(OR(F12="",G12="",G12=0),"",F12/G12) -> 26.315789 | I12: =IF(F12="","",IFERROR(INDEX(Currais!$K$3:$K$8,MATCH(B12,Currais!$A$3:$A$8,0)),0)) -> 0.45771 | J12: =IF(F12="","",F12*I12) -> 457.71 | K12: Estimado — rampa
A13: 46212 | B13: 2 | C13: 440 | D13: 220 | E13: 440 | F13: =IF(AND(C13="",D13="",E13=""),"",N(C13)+N(D13)+N(E13)) -> 1100 | G13: =IF(B13="","",IFERROR(INDEX(Currais!$C$3:$C$8,MATCH(B13,Currais!$A$3:$A$8,0)),"")) -> 38 | H13: =IF(OR(F13="",G13="",G13=0),"",F13/G13) -> 28.947368 | I13: =IF(F13="","",IFERROR(INDEX(Currais!$K$3:$K$8,MATCH(B13,Currais!$A$3:$A$8,0)),0)) -> 0.45771 | J13: =IF(F13="","",F13*I13) -> 503.481 | K13: Estimado — rampa
A14: 46213 | B14: 2 | C14: 440 | D14: 220 | E14: 440 | F14: =IF(AND(C14="",D14="",E14=""),"",N(C14)+N(D14)+N(E14)) -> 1100 | G14: =IF(B14="","",IFERROR(INDEX(Currais!$C$3:$C$8,MATCH(B14,Currais!$A$3:$A$8,0)),"")) -> 38 | H14: =IF(OR(F14="",G14="",G14=0),"",F14/G14) -> 28.947368 | I14: =IF(F14="","",IFERROR(INDEX(Currais!$K$3:$K$8,MATCH(B14,Currais!$A$3:$A$8,0)),0)) -> 0.45771 | J14: =IF(F14="","",F14*I14) -> 503.481 | K14: Estimado — rampa
A15: 46214 | B15: 2 | C15: 440 | D15: 220 | E15: 440 | F15: =IF(AND(C15="",D15="",E15=""),"",N(C15)+N(D15)+N(E15)) -> 1100 | G15: =IF(B15="","",IFERROR(INDEX(Currais!$C$3:$C$8,MATCH(B15,Currais!$A$3:$A$8,0)),"")) -> 38 | H15: =IF(OR(F15="",G15="",G15=0),"",F15/G15) -> 28.947368 | I15: =IF(F15="","",IFERROR(INDEX(Currais!$K$3:$K$8,MATCH(B15,Currais!$A$3:$A$8,0)),0)) -> 0.45771 | J15: =IF(F15="","",F15*I15) -> 503.481 | K15: Estimado — rampa
... A147: 46237 | B147: 4-TN | C147: 280 | D147: 140 | E147: 280 | F147: =IF(AND(C147="",D147="",E147=""),"",N(C147)+N(D147)+N(E147)) -> 700 | G147: =IF(B147="","",IFERROR(INDEX(Currais!$C$3:$C$8,MATCH(B147,Currais!$A$3:$A$8,0)),"")) -> 29 | H147: =IF(OR(F147="",G147="",G147=0),"",F147/G147) -> 24.137931 | I147: =IF(F147="","",IFERROR(INDEX(Currais!$K$3:$K$8,MATCH(B147,Currais!$A$3:$A$8,0)),0)) -> 0.66905 | J147: =IF(F147="","",F147*I147) -> 468.335 | K147: Estimado — constante
A148: 46238 | B148: 4-TN | C148: 280 | D148: 140 | E148: 280 | F148: =IF(AND(C148="",D148="",E148=""),"",N(C148)+N(D148)+N(E148)) -> 700 | G148: =IF(B148="","",IFERROR(INDEX(Currais!$C$3:$C$8,MATCH(B148,Currais!$A$3:$A$8,0)),"")) -> 29 | H148: =IF(OR(F148="",G148="",G148=0),"",F148/G148) -> 24.137931 | I148: =IF(F148="","",IFERROR(INDEX(Currais!$K$3:$K$8,MATCH(B148,Currais!$A$3:$A$8,0)),0)) -> 0.66905 | J148: =IF(F148="","",F148*I148) -> 468.335
A149: 46239 | B149: 4-TN | C149: 280 | D149: 140 | E149: 280 | F149: =IF(AND(C149="",D149="",E149=""),"",N(C149)+N(D149)+N(E149)) -> 700 | G149: =IF(B149="","",IFERROR(INDEX(Currais!$C$3:$C$8,MATCH(B149,Currais!$A$3:$A$8,0)),"")) -> 29 | H149: =IF(OR(F149="",G149="",G149=0),"",F149/G149) -> 24.137931 | I149: =IF(F149="","",IFERROR(INDEX(Currais!$K$3:$K$8,MATCH(B149,Currais!$A$3:$A$8,0)),0)) -> 0.66905 | J149: =IF(F149="","",F149*I149) -> 468.335
A150: 46240 | B150: 4-TN | C150: 280 | D150: 140 | E150: 280 | F150: =IF(AND(C150="",D150="",E150=""),"",N(C150)+N(D150)+N(E150)) -> 700 | G150: =IF(B150="","",IFERROR(INDEX(Currais!$C$3:$C$8,MATCH(B150,Currais!$A$3:$A$8,0)),"")) -> 29 | H150: =IF(OR(F150="",G150="",G150=0),"",F150/G150) -> 24.137931 | I150: =IF(F150="","",IFERROR(INDEX(Currais!$K$3:$K$8,MATCH(B150,Currais!$A$3:$A$8,0)),0)) -> 0.66905 | J150: =IF(F150="","",F150*I150) -> 468.335
A151: 46241 | B151: 4-TN | C151: 280 | D151: 140 | E151: 280 | F151: =IF(AND(C151="",D151="",E151=""),"",N(C151)+N(D151)+N(E151)) -> 700 | G151: =IF(B151="","",IFERROR(INDEX(Currais!$C$3:$C$8,MATCH(B151,Currais!$A$3:$A$8,0)),"")) -> 29 | H151: =IF(OR(F151="",G151="",G151=0),"",F151/G151) -> 24.137931 | I151: =IF(F151="","",IFERROR(INDEX(Currais!$K$3:$K$8,MATCH(B151,Currais!$A$3:$A$8,0)),0)) -> 0.66905 | J151: =IF(F151="","",F151*I151) -> 468.335
A152: 46242 | B152: 4-TN | C152: 280 | D152: 140 | E152: 280 | F152: =IF(AND(C152="",D152="",E152=""),"",N(C152)+N(D152)+N(E152)) -> 700 | G152: =IF(B152="","",IFERROR(INDEX(Currais!$C$3:$C$8,MATCH(B152,Currais!$A$3:$A$8,0)),"")) -> 29 | H152: =IF(OR(F152="",G152="",G152=0),"",F152/G152) -> 24.137931 | I152: =IF(F152="","",IFERROR(INDEX(Currais!$K$3:$K$8,MATCH(B152,Currais!$A$3:$A$8,0)),0)) -> 0.66905 | J152: =IF(F152="","",F152*I152) -> 468.335
A153: 46243 | B153: 4-TN | C153: 280 | D153: 140 | E153: 280 | F153: =IF(AND(C153="",D153="",E153=""),"",N(C153)+N(D153)+N(E153)) -> 700 | G153: =IF(B153="","",IFERROR(INDEX(Currais!$C$3:$C$8,MATCH(B153,Currais!$A$3:$A$8,0)),"")) -> 29 | H153: =IF(OR(F153="",G153="",G153=0),"",F153/G153) -> 24.137931 | I153: =IF(F153="","",IFERROR(INDEX(Currais!$K$3:$K$8,MATCH(B153,Currais!$A$3:$A$8,0)),0)) -> 0.66905 | J153: =IF(F153="","",F153*I153) -> 468.335
A154: 46244 | B154: 4-TN | C154: 280 | D154: 140 | E154: 280 | F154: =IF(AND(C154="",D154="",E154=""),"",N(C154)+N(D154)+N(E154)) -> 700 | G154: =IF(B154="","",IFERROR(INDEX(Currais!$C$3:$C$8,MATCH(B154,Currais!$A$3:$A$8,0)),"")) -> 29 | H154: =IF(OR(F154="",G154="",G154=0),"",F154/G154) -> 24.137931 | I154: =IF(F154="","",IFERROR(INDEX(Currais!$K$3:$K$8,MATCH(B154,Currais!$A$3:$A$8,0)),0)) -> 0.66905 | J154: =IF(F154="","",F154*I154) -> 468.335
A155: 46245 | B155: 4-TN | C155: 280 | D155: 140 | E155: 280 | F155: =IF(AND(C155="",D155="",E155=""),"",N(C155)+N(D155)+N(E155)) -> 700 | G155: =IF(B155="","",IFERROR(INDEX(Currais!$C$3:$C$8,MATCH(B155,Currais!$A$3:$A$8,0)),"")) -> 29 | H155: =IF(OR(F155="",G155="",G155=0),"",F155/G155) -> 24.137931 | I155: =IF(F155="","",IFERROR(INDEX(Currais!$K$3:$K$8,MATCH(B155,Currais!$A$3:$A$8,0)),0)) -> 0.66905 | J155: =IF(F155="","",F155*I155) -> 468.335
F156: =IF(AND(C156="",D156="",E156=""),"",N(C156)+N(D156)+N(E156)) | G156: =IF(B156="","",IFERROR(INDEX(Currais!$C$3:$C$8,MATCH(B156,Currais!$A$3:$A$8,0)),"")) | H156: =IF(OR(F156="",G156="",G156=0),"",F156/G156) | I156: =IF(F156="","",IFERROR(INDEX(Currais!$K$3:$K$8,MATCH(B156,Currais!$A$3:$A$8,0)),0)) | J156: =IF(F156="","",F156*I156)
F157: =IF(AND(C157="",D157="",E157=""),"",N(C157)+N(D157)+N(E157)) | G157: =IF(B157="","",IFERROR(INDEX(Currais!$C$3:$C$8,MATCH(B157,Currais!$A$3:$A$8,0)),"")) | H157: =IF(OR(F157="",G157="",G157=0),"",F157/G157) | I157: =IF(F157="","",IFERROR(INDEX(Currais!$K$3:$K$8,MATCH(B157,Currais!$A$3:$A$8,0)),0)) | J157: =IF(F157="","",F157*I157)
F158: =IF(AND(C158="",D158="",E158=""),"",N(C158)+N(D158)+N(E158)) | G158: =IF(B158="","",IFERROR(INDEX(Currais!$C$3:$C$8,MATCH(B158,Currais!$A$3:$A$8,0)),"")) | H158: =IF(OR(F158="",G158="",G158=0),"",F158/G158) | I158: =IF(F158="","",IFERROR(INDEX(Currais!$K$3:$K$8,MATCH(B158,Currais!$A$3:$A$8,0)),0)) | J158: =IF(F158="","",F158*I158)
F159: =IF(AND(C159="",D159="",E159=""),"",N(C159)+N(D159)+N(E159)) | G159: =IF(B159="","",IFERROR(INDEX(Currais!$C$3:$C$8,MATCH(B159,Currais!$A$3:$A$8,0)),"")) | H159: =IF(OR(F159="",G159="",G159=0),"",F159/G159) | I159: =IF(F159="","",IFERROR(INDEX(Currais!$K$3:$K$8,MATCH(B159,Currais!$A$3:$A$8,0)),0)) | J159: =IF(F159="","",F159*I159)
F160: =IF(AND(C160="",D160="",E160=""),"",N(C160)+N(D160)+N(E160)) | G160: =IF(B160="","",IFERROR(INDEX(Currais!$C$3:$C$8,MATCH(B160,Currais!$A$3:$A$8,0)),"")) | H160: =IF(OR(F160="",G160="",G160=0),"",F160/G160) | I160: =IF(F160="","",IFERROR(INDEX(Currais!$K$3:$K$8,MATCH(B160,Currais!$A$3:$A$8,0)),0)) | J160: =IF(F160="","",F160*I160)
F161: =IF(AND(C161="",D161="",E161=""),"",N(C161)+N(D161)+N(E161)) | G161: =IF(B161="","",IFERROR(INDEX(Currais!$C$3:$C$8,MATCH(B161,Currais!$A$3:$A$8,0)),"")) | H161: =IF(OR(F161="",G161="",G161=0),"",F161/G161) | I161: =IF(F161="","",IFERROR(INDEX(Currais!$K$3:$K$8,MATCH(B161,Currais!$A$3:$A$8,0)),0)) | J161: =IF(F161="","",F161*I161)
F162: =IF(AND(C162="",D162="",E162=""),"",N(C162)+N(D162)+N(E162)) | G162: =IF(B162="","",IFERROR(INDEX(Currais!$C$3:$C$8,MATCH(B162,Currais!$A$3:$A$8,0)),"")) | H162: =IF(OR(F162="",G162="",G162=0),"",F162/G162) | I162: =IF(F162="","",IFERROR(INDEX(Currais!$K$3:$K$8,MATCH(B162,Currais!$A$3:$A$8,0)),0)) | J162: =IF(F162="","",F162*I162)
F163: =IF(AND(C163="",D163="",E163=""),"",N(C163)+N(D163)+N(E163)) | G163: =IF(B163="","",IFERROR(INDEX(Currais!$C$3:$C$8,MATCH(B163,Currais!$A$3:$A$8,0)),"")) | H163: =IF(OR(F163="",G163="",G163=0),"",F163/G163) | I163: =IF(F163="","",IFERROR(INDEX(Currais!$K$3:$K$8,MATCH(B163,Currais!$A$3:$A$8,0)),0)) | J163: =IF(F163="","",F163*I163)
F164: =IF(AND(C164="",D164="",E164=""),"",N(C164)+N(D164)+N(E164)) | G164: =IF(B164="","",IFERROR(INDEX(Currais!$C$3:$C$8,MATCH(B164,Currais!$A$3:$A$8,0)),"")) | H164: =IF(OR(F164="",G164="",G164=0),"",F164/G164) | I164: =IF(F164="","",IFERROR(INDEX(Currais!$K$3:$K$8,MATCH(B164,Currais!$A$3:$A$8,0)),0)) | J164: =IF(F164="","",F164*I164)
F165: =IF(AND(C165="",D165="",E165=""),"",N(C165)+N(D165)+N(E165)) | G165: =IF(B165="","",IFERROR(INDEX(Currais!$C$3:$C$8,MATCH(B165,Currais!$A$3:$A$8,0)),"")) | H165: =IF(OR(F165="",G165="",G165=0),"",F165/G165) | I165: =IF(F165="","",IFERROR(INDEX(Currais!$K$3:$K$8,MATCH(B165,Currais!$A$3:$A$8,0)),0)) | J165: =IF(F165="","",F165*I165)
F166: =IF(AND(C166="",D166="",E166=""),"",N(C166)+N(D166)+N(E166)) | G166: =IF(B166="","",IFERROR(INDEX(Currais!$C$3:$C$8,MATCH(B166,Currais!$A$3:$A$8,0)),"")) | H166: =IF(OR(F166="",G166="",G166=0),"",F166/G166) | I166: =IF(F166="","",IFERROR(INDEX(Currais!$K$3:$K$8,MATCH(B166,Currais!$A$3:$A$8,0)),0)) | J166: =IF(F166="","",F166*I166)
F167: =IF(AND(C167="",D167="",E167=""),"",N(C167)+N(D167)+N(E167)) | G167: =IF(B167="","",IFERROR(INDEX(Currais!$C$3:$C$8,MATCH(B167,Currais!$A$3:$A$8,0)),"")) | H167: =IF(OR(F167="",G167="",G167=0),"",F167/G167) | I167: =IF(F167="","",IFERROR(INDEX(Currais!$K$3:$K$8,MATCH(B167,Currais!$A$3:$A$8,0)),0)) | J167: =IF(F167="","",F167*I167)
... F203: =IF(AND(C203="",D203="",E203=""),"",N(C203)+N(D203)+N(E203)) | G203: =IF(B203="","",IFERROR(INDEX(Currais!$C$3:$C$8,MATCH(B203,Currais!$A$3:$A$8,0)),"")) | H203: =IF(OR(F203="",G203="",G203=0),"",F203/G203) | I203: =IF(F203="","",IFERROR(INDEX(Currais!$K$3:$K$8,MATCH(B203,Currais!$A$3:$A$8,0)),0)) | J203: =IF(F203="","",F203*I203)

Sheet Custo_Nutricao_Lote
B2: CUSTO DE NUTRIÇÃO POR LOTE (CURRAL) — BG
B3: Estimativa = consumo planejado/dia (Calculadora) × dias de confinamento × custo da dieta do curral. Real = soma dos lançamentos do Trato_Diario. @ produzidas vêm das pesagens.
B5: Lote (Curral) | C5: Nº Cab | D5: Dias Conf | E5: Consumo Planej./dia (kg MN) | F5: Custo Dieta (R$/kg) | G5: Custo Ração/dia (R$) | H5: Custo/cab/dia (R$) | I5: Custo Estim. Acum. (R$) | J5: Custo Real Acum. (R$) | K5: Custo/cab Acum. (R$) | L5: @ Produzidas | M5: Custo Estim./@ (R$)
B6: 2 | C6: =IFERROR(INDEX(Currais!$C$3:$C$8,MATCH(B6,Currais!$A$3:$A$8,0)),0) -> 38 | D6: =IFERROR(Parâmetros!$C$4-_xlfn.MINIFS(Cadastro_Animais!$F$3:$F$5001,Cadastro_Animais!$E$3:$E$5001,B6),"") -> 43 | E6: =IFERROR(INDEX(Calculadora_Trato!$I$8:$I$13,MATCH(B6,Calculadora_Trato!$B$8:$B$13,0)),0) -> 503.28 | F6: =IFERROR(INDEX(Currais!$K$3:$K$8,MATCH(B6,Currais!$A$3:$A$8,0)),0) -> 0.45771 | G6: =E6*F6 -> 230.35629 | H6: =IF(C6=0,"",G6/C6) -> 6.0620076 | I6: =IF(D6="","",G6*D6) -> 9905.3204 | J6: =SUMIFS(Trato_Diario!$J$4:$J$203,Trato_Diario!$B$4:$B$203,B6) -> 18766.11 | K6: =IF(C6=0,"",I6/C6) -> 260.66633 | L6: =SUMIFS(Cadastro_Animais!$N$3:$N$5001,Cadastro_Animais!$E$3:$E$5001,B6) -> 0 | M6: =IF(L6<=0,"",I6/L6)
B7: 3 | C7: =IFERROR(INDEX(Currais!$C$3:$C$8,MATCH(B7,Currais!$A$3:$A$8,0)),0) -> 46 | D7: =IFERROR(Parâmetros!$C$4-_xlfn.MINIFS(Cadastro_Animais!$F$3:$F$5001,Cadastro_Animais!$E$3:$E$5001,B7),"") -> 43 | E7: =IFERROR(INDEX(Calculadora_Trato!$I$8:$I$13,MATCH(B7,Calculadora_Trato!$B$8:$B$13,0)),0) -> 575.136 | F7: =IFERROR(INDEX(Currais!$K$3:$K$8,MATCH(B7,Currais!$A$3:$A$8,0)),0) -> 0.45771 | G7: =E7*F7 -> 263.2455 | H7: =IF(C7=0,"",G7/C7) -> 5.7227282 | I7: =IF(D7="","",G7*D7) -> 11319.556 | J7: =SUMIFS(Trato_Diario!$J$4:$J$203,Trato_Diario!$B$4:$B$203,B7) -> 17164.125 | K7: =IF(C7=0,"",I7/C7) -> 246.07731 | L7: =SUMIFS(Cadastro_Animais!$N$3:$N$5001,Cadastro_Animais!$E$3:$E$5001,B7) -> 114.97467 | M7: =IF(L7<=0,"",I7/L7) -> 98.452614
B8: 4 | C8: =IFERROR(INDEX(Currais!$C$3:$C$8,MATCH(B8,Currais!$A$3:$A$8,0)),0) -> 165 | D8: =IFERROR(Parâmetros!$C$4-_xlfn.MINIFS(Cadastro_Animais!$F$3:$F$5001,Cadastro_Animais!$E$3:$E$5001,B8),"") -> 47 | E8: =IFERROR(INDEX(Calculadora_Trato!$I$8:$I$13,MATCH(B8,Calculadora_Trato!$B$8:$B$13,0)),0) -> 869.928 | F8: =IFERROR(INDEX(Currais!$K$3:$K$8,MATCH(B8,Currais!$A$3:$A$8,0)),0) -> 0.52245 | G8: =E8*F8 -> 454.49388 | H8: =IF(C8=0,"",G8/C8) -> 2.7545084 | I8: =IF(D8="","",G8*D8) -> 21361.213 | J8: =SUMIFS(Trato_Diario!$J$4:$J$203,Trato_Diario!$B$4:$B$203,B8) -> 45923.355 | K8: =IF(C8=0,"",I8/C8) -> 129.46189 | L8: =SUMIFS(Cadastro_Animais!$N$3:$N$5001,Cadastro_Animais!$E$3:$E$5001,B8) -> 0 | M8: =IF(L8<=0,"",I8/L8)
B9: 4-TN | C9: =IFERROR(INDEX(Currais!$C$3:$C$8,MATCH(B9,Currais!$A$3:$A$8,0)),0) -> 29 | D9: =IFERROR(Parâmetros!$C$4-_xlfn.MINIFS(Cadastro_Animais!$F$3:$F$5001,Cadastro_Animais!$E$3:$E$5001,B9),"") -> 43 | E9: =IFERROR(INDEX(Calculadora_Trato!$I$8:$I$13,MATCH(B9,Calculadora_Trato!$B$8:$B$13,0)),0) -> 388.872 | F9: =IFERROR(INDEX(Currais!$K$3:$K$8,MATCH(B9,Currais!$A$3:$A$8,0)),0) -> 0.66905 | G9: =E9*F9 -> 260.17481 | H9: =IF(C9=0,"",G9/C9) -> 8.9715452 | I9: =IF(D9="","",G9*D9) -> 11187.517 | J9: =SUMIFS(Trato_Diario!$J$4:$J$203,Trato_Diario!$B$4:$B$203,B9) -> 20138.405 | K9: =IF(C9=0,"",I9/C9) -> 385.77644 | L9: =SUMIFS(Cadastro_Animais!$N$3:$N$5001,Cadastro_Animais!$E$3:$E$5001,B9) -> 96.848667 | M9: =IF(L9<=0,"",I9/L9) -> 115.51545
B10: (a definir) | C10: =IFERROR(INDEX(Currais!$C$3:$C$8,MATCH(B10,Currais!$A$3:$A$8,0)),0) -> 70 | D10: =IFERROR(Parâmetros!$C$4-_xlfn.MINIFS(Cadastro_Animais!$F$3:$F$5001,Cadastro_Animais!$E$3:$E$5001,B10),"") -> 21 | E10: =IFERROR(INDEX(Calculadora_Trato!$I$8:$I$13,MATCH(B10,Calculadora_Trato!$B$8:$B$13,0)),0) -> 574.608 | F10: =IFERROR(INDEX(Currais!$K$3:$K$8,MATCH(B10,Currais!$A$3:$A$8,0)),0) -> 0.66905 | G10: =E10*F10 -> 384.44148 | H10: =IF(C10=0,"",G10/C10) -> 5.4920212 | I10: =IF(D10="","",G10*D10) -> 8073.2711 | J10: =SUMIFS(Trato_Diario!$J$4:$J$203,Trato_Diario!$B$4:$B$203,B10) -> 0 | K10: =IF(C10=0,"",I10/C10) -> 115.33244 | L10: =SUMIFS(Cadastro_Animais!$N$3:$N$5001,Cadastro_Animais!$E$3:$E$5001,B10) -> 0 | M10: =IF(L10<=0,"",I10/L10)
B11: 5 | C11: =IFERROR(INDEX(Currais!$C$3:$C$8,MATCH(B11,Currais!$A$3:$A$8,0)),0) -> 37 | D11: =IFERROR(Parâmetros!$C$4-_xlfn.MINIFS(Cadastro_Animais!$F$3:$F$5001,Cadastro_Animais!$E$3:$E$5001,B11),"") -> 14 | E11: =IFERROR(INDEX(Calculadora_Trato!$I$8:$I$13,MATCH(B11,Calculadora_Trato!$B$8:$B$13,0)),0) -> 312.12 | F11: =IFERROR(INDEX(Currais!$K$3:$K$8,MATCH(B11,Currais!$A$3:$A$8,0)),0) -> 0.57515 | G11: =E11*F11 -> 179.51582 | H11: =IF(C11=0,"",G11/C11) -> 4.8517789 | I11: =IF(D11="","",G11*D11) -> 2513.2215 | J11: =SUMIFS(Trato_Diario!$J$4:$J$203,Trato_Diario!$B$4:$B$203,B11) -> 0 | K11: =IF(C11=0,"",I11/C11) -> 67.924904 | L11: =SUMIFS(Cadastro_Animais!$N$3:$N$5001,Cadastro_Animais!$E$3:$E$5001,B11) -> 0 | M11: =IF(L11<=0,"",I11/L11)
B12: TOTAL | C12: =SUM(C6:C11) -> 385 | G12: =SUM(G6:G11) -> 1772.2278 | H12: =IF(C12=0,"",G12/C12) -> 4.603189 | I12: =SUM(I6:I11) -> 64360.099 | J12: =SUM(J6:J11) -> 101992 | K12: =IF(C12=0,"",I12/C12) -> 167.16909 | L12: =SUM(L6:L11) -> 211.82333 | M12: =IF(L12<=0,"",I12/L12) -> 303.83857

Sheet Custo_Diario_Cab
A1: CUSTO MÉDIO DIÁRIO DE RAÇÃO POR CABEÇA — POR CURRAL (BG)
A2: Custo REAL de ração por cabeça por dia (custo do trato do dia ÷ nº de cabeças). A MÉDIA DIÁRIA = custo total do período ÷ (dias × cabeças) de cada curral. Atualiza conforme você lança tratos. Novilhas e Descarte aparecem quando você lançar os tratos deles.
B4: 2 — Bonsmara R1 | C4: 3 — Bonsmara R2 | D4: 4 — Bezerros | E4: 4-TN — Nelore | F4: Novilhas | G4: 5 — Descarte | H4: Rebanho
A5: Curral (ref.) | B5: 2 | C5: 3 | D5: 4 | E5: 4-TN | F5: (a definir) | G5: 5
A6: Nº cabeças | B6: =IFERROR(INDEX(Currais!$C$3:$C$8,MATCH(B$5,Currais!$A$3:$A$8,0)),0) -> 38 | C6: =IFERROR(INDEX(Currais!$C$3:$C$8,MATCH(C$5,Currais!$A$3:$A$8,0)),0) -> 46 | D6: =IFERROR(INDEX(Currais!$C$3:$C$8,MATCH(D$5,Currais!$A$3:$A$8,0)),0) -> 165 | E6: =IFERROR(INDEX(Currais!$C$3:$C$8,MATCH(E$5,Currais!$A$3:$A$8,0)),0) -> 29 | F6: =IFERROR(INDEX(Currais!$C$3:$C$8,MATCH(F$5,Currais!$A$3:$A$8,0)),0) -> 70 | G6: =IFERROR(INDEX(Currais!$C$3:$C$8,MATCH(G$5,Currais!$A$3:$A$8,0)),0) -> 37 | H6: =SUM(B6:G6) -> 385
A7: Dias com trato | B7: =COUNTIFS(Trato_Diario!$B$4:$B$203,B$5,Trato_Diario!$F$4:$F$203,"<>") -> 35 | C7: =COUNTIFS(Trato_Diario!$B$4:$B$203,C$5,Trato_Diario!$F$4:$F$203,"<>") -> 35 | D7: =COUNTIFS(Trato_Diario!$B$4:$B$203,D$5,Trato_Diario!$F$4:$F$203,"<>") -> 39 | E7: =COUNTIFS(Trato_Diario!$B$4:$B$203,E$5,Trato_Diario!$F$4:$F$203,"<>") -> 43 | F7: =COUNTIFS(Trato_Diario!$B$4:$B$203,F$5,Trato_Diario!$F$4:$F$203,"<>") -> 0 | G7: =COUNTIFS(Trato_Diario!$B$4:$B$203,G$5,Trato_Diario!$F$4:$F$203,"<>") -> 0
A8: MÉDIA DIÁRIA (R$/cab/dia) | B8: =IFERROR(SUMIFS(Trato_Diario!$J$4:$J$203,Trato_Diario!$B$4:$B$203,B$5)/SUMIFS(Trato_Diario!$G$4:$G$203,Trato_Diario!$B$4:$B$203,B$5),"") -> 14.109857 | C8: =IFERROR(SUMIFS(Trato_Diario!$J$4:$J$203,Trato_Diario!$B$4:$B$203,C$5)/SUMIFS(Trato_Diario!$G$4:$G$203,Trato_Diario!$B$4:$B$203,C$5),"") -> 10.660947 | D8: =IFERROR(SUMIFS(Trato_Diario!$J$4:$J$203,Trato_Diario!$B$4:$B$203,D$5)/SUMIFS(Trato_Diario!$G$4:$G$203,Trato_Diario!$B$4:$B$203,D$5),"") -> 7.1364965 | E8: =IFERROR(SUMIFS(Trato_Diario!$J$4:$J$203,Trato_Diario!$B$4:$B$203,E$5)/SUMIFS(Trato_Diario!$G$4:$G$203,Trato_Diario!$B$4:$B$203,E$5),"") -> 16.149483 | F8: =IFERROR(SUMIFS(Trato_Diario!$J$4:$J$203,Trato_Diario!$B$4:$B$203,F$5)/SUMIFS(Trato_Diario!$G$4:$G$203,Trato_Diario!$B$4:$B$203,F$5),"") | G8: =IFERROR(SUMIFS(Trato_Diario!$J$4:$J$203,Trato_Diario!$B$4:$B$203,G$5)/SUMIFS(Trato_Diario!$G$4:$G$203,Trato_Diario!$B$4:$B$203,G$5),"") | H8: =IFERROR(SUM(Trato_Diario!$J$4:$J$203)/SUM(Trato_Diario!$G$4:$G$203),"") -> 9.6019577
A10: DETALHE DIA A DIA — custo do dia por cabeça (R$/cab/dia)
A11: Data | B11: 2 — Bonsmara R1 | C11: 3 — Bonsmara R2 | D11: 4 — Bezerros | E11: 4-TN — Nelore | F11: Novilhas | G11: 5 — Descarte | H11: Rebanho
A12: 46199 | B12: =IF(OR($A12>MAX(Trato_Diario!$A$4:$A$203),SUMIFS(Trato_Diario!$G$4:$G$203,Trato_Diario!$B$4:$B$203,B$5,Trato_Diario!$A$4:$A$203,$A12)=0),"",SUMIFS(Trato_Diario!$J$4:$J$203,Trato_Diario!$B$4:$B$203,B$5,Trato_Diario!$A$4:$A$203,$A12)/SUMIFS(Trato_Diario!$G$4:$G$203,Trato_Diario!$B$4:$B$203,B$5,Trato_Diario!$A$4:$A$203,$A12)) | C12: =IF(OR($A12>MAX(Trato_Diario!$A$4:$A$203),SUMIFS(Trato_Diario!$G$4:$G$203,Trato_Diario!$B$4:$B$203,C$5,Trato_Diario!$A$4:$A$203,$A12)=0),"",SUMIFS(Trato_Diario!$J$4:$J$203,Trato_Diario!$B$4:$B$203,C$5,Trato_Diario!$A$4:$A$203,$A12)/SUMIFS(Trato_Diario!$G$4:$G$203,Trato_Diario!$B$4:$B$203,C$5,Trato_Diario!$A$4:$A$203,$A12)) | D12: =IF(OR($A12>MAX(Trato_Diario!$A$4:$A$203),SUMIFS(Trato_Diario!$G$4:$G$203,Trato_Diario!$B$4:$B$203,D$5,Trato_Diario!$A$4:$A$203,$A12)=0),"",SUMIFS(Trato_Diario!$J$4:$J$203,Trato_Diario!$B$4:$B$203,D$5,Trato_Diario!$A$4:$A$203,$A12)/SUMIFS(Trato_Diario!$G$4:$G$203,Trato_Diario!$B$4:$B$203,D$5,Trato_Diario!$A$4:$A$203,$A12)) -> 5.3828182 | E12: =IF(OR($A12>MAX(Trato_Diario!$A$4:$A$203),SUMIFS(Trato_Diario!$G$4:$G$203,Trato_Diario!$B$4:$B$203,E$5,Trato_Diario!$A$4:$A$203,$A12)=0),"",SUMIFS(Trato_Diario!$J$4:$J$203,Trato_Diario!$B$4:$B$203,E$5,Trato_Diario!$A$4:$A$203,$A12)/SUMIFS(Trato_Diario!$G$4:$G$203,Trato_Diario!$B$4:$B$203,E$5,Trato_Diario!$A$4:$A$203,$A12)) | F12: =IF(OR($A12>MAX(Trato_Diario!$A$4:$A$203),SUMIFS(Trato_Diario!$G$4:$G$203,Trato_Diario!$B$4:$B$203,F$5,Trato_Diario!$A$4:$A$203,$A12)=0),"",SUMIFS(Trato_Diario!$J$4:$J$203,Trato_Diario!$B$4:$B$203,F$5,Trato_Diario!$A$4:$A$203,$A12)/SUMIFS(Trato_Diario!$G$4:$G$203,Trato_Diario!$B$4:$B$203,F$5,Trato_Diario!$A$4:$A$203,$A12)) | G12: =IF(OR($A12>MAX(Trato_Diario!$A$4:$A$203),SUMIFS(Trato_Diario!$G$4:$G$203,Trato_Diario!$B$4:$B$203,G$5,Trato_Diario!$A$4:$A$203,$A12)=0),"",SUMIFS(Trato_Diario!$J$4:$J$203,Trato_Diario!$B$4:$B$203,G$5,Trato_Diario!$A$4:$A$203,$A12)/SUMIFS(Trato_Diario!$G$4:$G$203,Trato_Diario!$B$4:$B$203,G$5,Trato_Diario!$A$4:$A$203,$A12)) | H12: =IF(OR($A12>MAX(Trato_Diario!$A$4:$A$203),SUMIFS(Trato_Diario!$G$4:$G$203,Trato_Diario!$A$4:$A$203,$A12)=0),"",SUMIFS(Trato_Diario!$J$4:$J$203,Trato_Diario!$A$4:$A$203,$A12)/SUMIFS(Trato_Diario!$G$4:$G$203,Trato_Diario!$A$4:$A$203,$A12)) -> 5.3828182
A13: 46200 | B13: =IF(OR($A13>MAX(Trato_Diario!$A$4:$A$203),SUMIFS(Trato_Diario!$G$4:$G$203,Trato_Diario!$B$4:$B$203,B$5,Trato_Diario!$A$4:$A$203,$A13)=0),"",SUMIFS(Trato_Diario!$J$4:$J$203,Trato_Diario!$B$4:$B$203,B$5,Trato_Diario!$A$4:$A$203,$A13)/SUMIFS(Trato_Diario!$G$4:$G$203,Trato_Diario!$B$4:$B$203,B$5,Trato_Diario!$A$4:$A$203,$A13)) | C13: =IF(OR($A13>MAX(Trato_Diario!$A$4:$A$203),SUMIFS(Trato_Diario!$G$4:$G$203,Trato_Diario!$B$4:$B$203,C$5,Trato_Diario!$A$4:$A$203,$A13)=0),"",SUMIFS(Trato_Diario!$J$4:$J$203,Trato_Diario!$B$4:$B$203,C$5,Trato_Diario!$A$4:$A$203,$A13)/SUMIFS(Trato_Diario!$G$4:$G$203,Trato_Diario!$B$4:$B$203,C$5,Trato_Diario!$A$4:$A$203,$A13)) | D13: =IF(OR($A13>MAX(Trato_Diario!$A$4:$A$203),SUMIFS(Trato_Diario!$G$4:$G$203,Trato_Diario!$B$4:$B$203,D$5,Trato_Diario!$A$4:$A$203,$A13)=0),"",SUMIFS(Trato_Diario!$J$4:$J$203,Trato_Diario!$B$4:$B$203,D$5,Trato_Diario!$A$4:$A$203,$A13)/SUMIFS(Trato_Diario!$G$4:$G$203,Trato_Diario!$B$4:$B$203,D$5,Trato_Diario!$A$4:$A$203,$A13)) -> 5.3828182 | E13: =IF(OR($A13>MAX(Trato_Diario!$A$4:$A$203),SUMIFS(Trato_Diario!$G$4:$G$203,Trato_Diario!$B$4:$B$203,E$5,Trato_Diario!$A$4:$A$203,$A13)=0),"",SUMIFS(Trato_Diario!$J$4:$J$203,Trato_Diario!$B$4:$B$203,E$5,Trato_Diario!$A$4:$A$203,$A13)/SUMIFS(Trato_Diario!$G$4:$G$203,Trato_Diario!$B$4:$B$203,E$5,Trato_Diario!$A$4:$A$203,$A13)) | F13: =IF(OR($A13>MAX(Trato_Diario!$A$4:$A$203),SUMIFS(Trato_Diario!$G$4:$G$203,Trato_Diario!$B$4:$B$203,F$5,Trato_Diario!$A$4:$A$203,$A13)=0),"",SUMIFS(Trato_Diario!$J$4:$J$203,Trato_Diario!$B$4:$B$203,F$5,Trato_Diario!$A$4:$A$203,$A13)/SUMIFS(Trato_Diario!$G$4:$G$203,Trato_Diario!$B$4:$B$203,F$5,Trato_Diario!$A$4:$A$203,$A13)) | G13: =IF(OR($A13>MAX(Trato_Diario!$A$4:$A$203),SUMIFS(Trato_Diario!$G$4:$G$203,Trato_Diario!$B$4:$B$203,G$5,Trato_Diario!$A$4:$A$203,$A13)=0),"",SUMIFS(Trato_Diario!$J$4:$J$203,Trato_Diario!$B$4:$B$203,G$5,Trato_Diario!$A$4:$A$203,$A13)/SUMIFS(Trato_Diario!$G$4:$G$203,Trato_Diario!$B$4:$B$203,G$5,Trato_Diario!$A$4:$A$203,$A13)) | H13: =IF(OR($A13>MAX(Trato_Diario!$A$4:$A$203),SUMIFS(Trato_Diario!$G$4:$G$203,Trato_Diario!$A$4:$A$203,$A13)=0),"",SUMIFS(Trato_Diario!$J$4:$J$203,Trato_Diario!$A$4:$A$203,$A13)/SUMIFS(Trato_Diario!$G$4:$G$203,Trato_Diario!$A$4:$A$203,$A13)) -> 5.3828182
A14: 46201 | B14: =IF(OR($A14>MAX(Trato_Diario!$A$4:$A$203),SUMIFS(Trato_Diario!$G$4:$G$203,Trato_Diario!$B$4:$B$203,B$5,Trato_Diario!$A$4:$A$203,$A14)=0),"",SUMIFS(Trato_Diario!$J$4:$J$203,Trato_Diario!$B$4:$B$203,B$5,Trato_Diario!$A$4:$A$203,$A14)/SUMIFS(Trato_Diario!$G$4:$G$203,Trato_Diario!$B$4:$B$203,B$5,Trato_Diario!$A$4:$A$203,$A14)) | C14: =IF(OR($A14>MAX(Trato_Diario!$A$4:$A$203),SUMIFS(Trato_Diario!$G$4:$G$203,Trato_Diario!$B$4:$B$203,C$5,Trato_Diario!$A$4:$A$203,$A14)=0),"",SUMIFS(Trato_Diario!$J$4:$J$203,Trato_Diario!$B$4:$B$203,C$5,Trato_Diario!$A$4:$A$203,$A14)/SUMIFS(Trato_Diario!$G$4:$G$203,Trato_Diario!$B$4:$B$203,C$5,Trato_Diario!$A$4:$A$203,$A14)) | D14: =IF(OR($A14>MAX(Trato_Diario!$A$4:$A$203),SUMIFS(Trato_Diario!$G$4:$G$203,Trato_Diario!$B$4:$B$203,D$5,Trato_Diario!$A$4:$A$203,$A14)=0),"",SUMIFS(Trato_Diario!$J$4:$J$203,Trato_Diario!$B$4:$B$203,D$5,Trato_Diario!$A$4:$A$203,$A14)/SUMIFS(Trato_Diario!$G$4:$G$203,Trato_Diario!$B$4:$B$203,D$5,Trato_Diario!$A$4:$A$203,$A14)) -> 5.3828182 | E14: =IF(OR($A14>MAX(Trato_Diario!$A$4:$A$203),SUMIFS(Trato_Diario!$G$4:$G$203,Trato_Diario!$B$4:$B$203,E$5,Trato_Diario!$A$4:$A$203,$A14)=0),"",SUMIFS(Trato_Diario!$J$4:$J$203,Trato_Diario!$B$4:$B$203,E$5,Trato_Diario!$A$4:$A$203,$A14)/SUMIFS(Trato_Diario!$G$4:$G$203,Trato_Diario!$B$4:$B$203,E$5,Trato_Diario!$A$4:$A$203,$A14)) | F14: =IF(OR($A14>MAX(Trato_Diario!$A$4:$A$203),SUMIFS(Trato_Diario!$G$4:$G$203,Trato_Diario!$B$4:$B$203,F$5,Trato_Diario!$A$4:$A$203,$A14)=0),"",SUMIFS(Trato_Diario!$J$4:$J$203,Trato_Diario!$B$4:$B$203,F$5,Trato_Diario!$A$4:$A$203,$A14)/SUMIFS(Trato_Diario!$G$4:$G$203,Trato_Diario!$B$4:$B$203,F$5,Trato_Diario!$A$4:$A$203,$A14)) | G14: =IF(OR($A14>MAX(Trato_Diario!$A$4:$A$203),SUMIFS(Trato_Diario!$G$4:$G$203,Trato_Diario!$B$4:$B$203,G$5,Trato_Diario!$A$4:$A$203,$A14)=0),"",SUMIFS(Trato_Diario!$J$4:$J$203,Trato_Diario!$B$4:$B$203,G$5,Trato_Diario!$A$4:$A$203,$A14)/SUMIFS(Trato_Diario!$G$4:$G$203,Trato_Diario!$B$4:$B$203,G$5,Trato_Diario!$A$4:$A$203,$A14)) | H14: =IF(OR($A14>MAX(Trato_Diario!$A$4:$A$203),SUMIFS(Trato_Diario!$G$4:$G$203,Trato_Diario!$A$4:$A$203,$A14)=0),"",SUMIFS(Trato_Diario!$J$4:$J$203,Trato_Diario!$A$4:$A$203,$A14)/SUMIFS(Trato_Diario!$G$4:$G$203,Trato_Diario!$A$4:$A$203,$A14)) -> 5.3828182
A15: 46202 | B15: =IF(OR($A15>MAX(Trato_Diario!$A$4:$A$203),SUMIFS(Trato_Diario!$G$4:$G$203,Trato_Diario!$B$4:$B$203,B$5,Trato_Diario!$A$4:$A$203,$A15)=0),"",SUMIFS(Trato_Diario!$J$4:$J$203,Trato_Diario!$B$4:$B$203,B$5,Trato_Diario!$A$4:$A$203,$A15)/SUMIFS(Trato_Diario!$G$4:$G$203,Trato_Diario!$B$4:$B$203,B$5,Trato_Diario!$A$4:$A$203,$A15)) | C15: =IF(OR($A15>MAX(Trato_Diario!$A$4:$A$203),SUMIFS(Trato_Diario!$G$4:$G$203,Trato_Diario!$B$4:$B$203,C$5,Trato_Diario!$A$4:$A$203,$A15)=0),"",SUMIFS(Trato_Diario!$J$4:$J$203,Trato_Diario!$B$4:$B$203,C$5,Trato_Diario!$A$4:$A$203,$A15)/SUMIFS(Trato_Diario!$G$4:$G$203,Trato_Diario!$B$4:$B$203,C$5,Trato_Diario!$A$4:$A$203,$A15)) | D15: =IF(OR($A15>MAX(Trato_Diario!$A$4:$A$203),SUMIFS(Trato_Diario!$G$4:$G$203,Trato_Diario!$B$4:$B$203,D$5,Trato_Diario!$A$4:$A$203,$A15)=0),"",SUMIFS(Trato_Diario!$J$4:$J$203,Trato_Diario!$B$4:$B$203,D$5,Trato_Diario!$A$4:$A$203,$A15)/SUMIFS(Trato_Diario!$G$4:$G$203,Trato_Diario!$B$4:$B$203,D$5,Trato_Diario!$A$4:$A$203,$A15)) -> 5.6994545 | E15: =IF(OR($A15>MAX(Trato_Diario!$A$4:$A$203),SUMIFS(Trato_Diario!$G$4:$G$203,Trato_Diario!$B$4:$B$203,E$5,Trato_Diario!$A$4:$A$203,$A15)=0),"",SUMIFS(Trato_Diario!$J$4:$J$203,Trato_Diario!$B$4:$B$203,E$5,Trato_Diario!$A$4:$A$203,$A15)/SUMIFS(Trato_Diario!$G$4:$G$203,Trato_Diario!$B$4:$B$203,E$5,Trato_Diario!$A$4:$A$203,$A15)) | F15: =IF(OR($A15>MAX(Trato_Diario!$A$4:$A$203),SUMIFS(Trato_Diario!$G$4:$G$203,Trato_Diario!$B$4:$B$203,F$5,Trato_Diario!$A$4:$A$203,$A15)=0),"",SUMIFS(Trato_Diario!$J$4:$J$203,Trato_Diario!$B$4:$B$203,F$5,Trato_Diario!$A$4:$A$203,$A15)/SUMIFS(Trato_Diario!$G$4:$G$203,Trato_Diario!$B$4:$B$203,F$5,Trato_Diario!$A$4:$A$203,$A15)) | G15: =IF(OR($A15>MAX(Trato_Diario!$A$4:$A$203),SUMIFS(Trato_Diario!$G$4:$G$203,Trato_Diario!$B$4:$B$203,G$5,Trato_Diario!$A$4:$A$203,$A15)=0),"",SUMIFS(Trato_Diario!$J$4:$J$203,Trato_Diario!$B$4:$B$203,G$5,Trato_Diario!$A$4:$A$203,$A15)/SUMIFS(Trato_Diario!$G$4:$G$203,Trato_Diario!$B$4:$B$203,G$5,Trato_Diario!$A$4:$A$203,$A15)) | H15: =IF(OR($A15>MAX(Trato_Diario!$A$4:$A$203),SUMIFS(Trato_Diario!$G$4:$G$203,Trato_Diario!$A$4:$A$203,$A15)=0),"",SUMIFS(Trato_Diario!$J$4:$J$203,Trato_Diario!$A$4:$A$203,$A15)/SUMIFS(Trato_Diario!$G$4:$G$203,Trato_Diario!$A$4:$A$203,$A15)) -> 5.6994545
A16: 46203 | B16: =IF(OR($A16>MAX(Trato_Diario!$A$4:$A$203),SUMIFS(Trato_Diario!$G$4:$G$203,Trato_Diario!$B$4:$B$203,B$5,Trato_Diario!$A$4:$A$203,$A16)=0),"",SUMIFS(Trato_Diario!$J$4:$J$203,Trato_Diario!$B$4:$B$203,B$5,Trato_Diario!$A$4:$A$203,$A16)/SUMIFS(Trato_Diario!$G$4:$G$203,Trato_Diario!$B$4:$B$203,B$5,Trato_Diario!$A$4:$A$203,$A16)) -> 9.636 | C16: =IF(OR($A16>MAX(Trato_Diario!$A$4:$A$203),SUMIFS(Trato_Diario!$G$4:$G$203,Trato_Diario!$B$4:$B$203,C$5,Trato_Diario!$A$4:$A$203,$A16)=0),"",SUMIFS(Trato_Diario!$J$4:$J$203,Trato_Diario!$B$4:$B$203,C$5,Trato_Diario!$A$4:$A$203,$A16)/SUMIFS(Trato_Diario!$G$4:$G$203,Trato_Diario!$B$4:$B$203,C$5,Trato_Diario!$A$4:$A$203,$A16)) -> 6.9651522 | D16: =IF(OR($A16>MAX(Trato_Diario!$A$4:$A$203),SUMIFS(Trato_Diario!$G$4:$G$203,Trato_Diario!$B$4:$B$203,D$5,Trato_Diario!$A$4:$A$203,$A16)=0),"",SUMIFS(Trato_Diario!$J$4:$J$203,Trato_Diario!$B$4:$B$203,D$5,Trato_Diario!$A$4:$A$203,$A16)/SUMIFS(Trato_Diario!$G$4:$G$203,Trato_Diario!$B$4:$B$203,D$5,Trato_Diario!$A$4:$A$203,$A16)) -> 5.6994545 | E16: =IF(OR($A16>MAX(Trato_Diario!$A$4:$A$203),SUMIFS(Trato_Diario!$G$4:$G$203,Trato_Diario!$B$4:$B$203,E$5,Trato_Diario!$A$4:$A$203,$A16)=0),"",SUMIFS(Trato_Diario!$J$4:$J$203,Trato_Diario!$B$4:$B$203,E$5,Trato_Diario!$A$4:$A$203,$A16)/SUMIFS(Trato_Diario!$G$4:$G$203,Trato_Diario!$B$4:$B$203,E$5,Trato_Diario!$A$4:$A$203,$A16)) -> 16.149483 | F16: =IF(OR($A16>MAX(Trato_Diario!$A$4:$A$203),SUMIFS(Trato_Diario!$G$4:$G$203,Trato_Diario!$B$4:$B$203,F$5,Trato_Diario!$A$4:$A$203,$A16)=0),"",SUMIFS(Trato_Diario!$J$4:$J$203,Trato_Diario!$B$4:$B$203,F$5,Trato_Diario!$A$4:$A$203,$A16)/SUMIFS(Trato_Diario!$G$4:$G$203,Trato_Diario!$B$4:$B$203,F$5,Trato_Diario!$A$4:$A$203,$A16)) | G16: =IF(OR($A16>MAX(Trato_Diario!$A$4:$A$203),SUMIFS(Trato_Diario!$G$4:$G$203,Trato_Diario!$B$4:$B$203,G$5,Trato_Diario!$A$4:$A$203,$A16)=0),"",SUMIFS(Trato_Diario!$J$4:$J$203,Trato_Diario!$B$4:$B$203,G$5,Trato_Diario!$A$4:$A$203,$A16)/SUMIFS(Trato_Diario!$G$4:$G$203,Trato_Diario!$B$4:$B$203,G$5,Trato_Diario!$A$4:$A$203,$A16)) | H16: =IF(OR($A16>MAX(Trato_Diario!$A$4:$A$203),SUMIFS(Trato_Diario!$G$4:$G$203,Trato_Diario!$A$4:$A$203,$A16)=0),"",SUMIFS(Trato_Diario!$J$4:$J$203,Trato_Diario!$A$4:$A$203,$A16)/SUMIFS(Trato_Diario!$G$4:$G$203,Trato_Diario!$A$4:$A$203,$A16)) -> 7.5370863
A17: 46204 | B17: =IF(OR($A17>MAX(Trato_Diario!$A$4:$A$203),SUMIFS(Trato_Diario!$G$4:$G$203,Trato_Diario!$B$4:$B$203,B$5,Trato_Diario!$A$4:$A$203,$A17)=0),"",SUMIFS(Trato_Diario!$J$4:$J$203,Trato_Diario!$B$4:$B$203,B$5,Trato_Diario!$A$4:$A$203,$A17)/SUMIFS(Trato_Diario!$G$4:$G$203,Trato_Diario!$B$4:$B$203,B$5,Trato_Diario!$A$4:$A$203,$A17)) -> 9.636 | C17: =IF(OR($A17>MAX(Trato_Diario!$A$4:$A$203),SUMIFS(Trato_Diario!$G$4:$G$203,Trato_Diario!$B$4:$B$203,C$5,Trato_Diario!$A$4:$A$203,$A17)=0),"",SUMIFS(Trato_Diario!$J$4:$J$203,Trato_Diario!$B$4:$B$203,C$5,Trato_Diario!$A$4:$A$203,$A17)/SUMIFS(Trato_Diario!$G$4:$G$203,Trato_Diario!$B$4:$B$203,C$5,Trato_Diario!$A$4:$A$203,$A17)) -> 6.9651522 | D17: =IF(OR($A17>MAX(Trato_Diario!$A$4:$A$203),SUMIFS(Trato_Diario!$G$4:$G$203,Trato_Diario!$B$4:$B$203,D$5,Trato_Diario!$A$4:$A$203,$A17)=0),"",SUMIFS(Trato_Diario!$J$4:$J$203,Trato_Diario!$B$4:$B$203,D$5,Trato_Diario!$A$4:$A$203,$A17)/SUMIFS(Trato_Diario!$G$4:$G$203,Trato_Diario!$B$4:$B$203,D$5,Trato_Diario!$A$4:$A$203,$A17)) -> 5.6994545 | E17: =IF(OR($A17>MAX(Trato_Diario!$A$4:$A$203),SUMIFS(Trato_Diario!$G$4:$G$203,Trato_Diario!$B$4:$B$203,E$5,Trato_Diario!$A$4:$A$203,$A17)=0),"",SUMIFS(Trato_Diario!$J$4:$J$203,Trato_Diario!$B$4:$B$203,E$5,Trato_Diario!$A$4:$A$203,$A17)/SUMIFS(Trato_Diario!$G$4:$G$203,Trato_Diario!$B$4:$B$203,E$5,Trato_Diario!$A$4:$A$203,$A17)) -> 16.149483 | F17: =IF(OR($A17>MAX(Trato_Diario!$A$4:$A$203),SUMIFS(Trato_Diario!$G$4:$G$203,Trato_Diario!$B$4:$B$203,F$5,Trato_Diario!$A$4:$A$203,$A17)=0),"",SUMIFS(Trato_Diario!$J$4:$J$203,Trato_Diario!$B$4:$B$203,F$5,Trato_Diario!$A$4:$A$203,$A17)/SUMIFS(Trato_Diario!$G$4:$G$203,Trato_Diario!$B$4:$B$203,F$5,Trato_Diario!$A$4:$A$203,$A17)) | G17: =IF(OR($A17>MAX(Trato_Diario!$A$4:$A$203),SUMIFS(Trato_Diario!$G$4:$G$203,Trato_Diario!$B$4:$B$203,G$5,Trato_Diario!$A$4:$A$203,$A17)=0),"",SUMIFS(Trato_Diario!$J$4:$J$203,Trato_Diario!$B$4:$B$203,G$5,Trato_Diario!$A$4:$A$203,$A17)/SUMIFS(Trato_Diario!$G$4:$G$203,Trato_Diario!$B$4:$B$203,G$5,Trato_Diario!$A$4:$A$203,$A17)) | H17: =IF(OR($A17>MAX(Trato_Diario!$A$4:$A$203),SUMIFS(Trato_Diario!$G$4:$G$203,Trato_Diario!$A$4:$A$203,$A17)=0),"",SUMIFS(Trato_Diario!$J$4:$J$203,Trato_Diario!$A$4:$A$203,$A17)/SUMIFS(Trato_Diario!$G$4:$G$203,Trato_Diario!$A$4:$A$203,$A17)) -> 7.5370863
A18: 46205 | B18: =IF(OR($A18>MAX(Trato_Diario!$A$4:$A$203),SUMIFS(Trato_Diario!$G$4:$G$203,Trato_Diario!$B$4:$B$203,B$5,Trato_Diario!$A$4:$A$203,$A18)=0),"",SUMIFS(Trato_Diario!$J$4:$J$203,Trato_Diario!$B$4:$B$203,B$5,Trato_Diario!$A$4:$A$203,$A18)/SUMIFS(Trato_Diario!$G$4:$G$203,Trato_Diario!$B$4:$B$203,B$5,Trato_Diario!$A$4:$A$203,$A18)) -> 9.636 | C18: =IF(OR($A18>MAX(Trato_Diario!$A$4:$A$203),SUMIFS(Trato_Diario!$G$4:$G$203,Trato_Diario!$B$4:$B$203,C$5,Trato_Diario!$A$4:$A$203,$A18)=0),"",SUMIFS(Trato_Diario!$J$4:$J$203,Trato_Diario!$B$4:$B$203,C$5,Trato_Diario!$A$4:$A$203,$A18)/SUMIFS(Trato_Diario!$G$4:$G$203,Trato_Diario!$B$4:$B$203,C$5,Trato_Diario!$A$4:$A$203,$A18)) -> 6.9651522 | D18: =IF(OR($A18>MAX(Trato_Diario!$A$4:$A$203),SUMIFS(Trato_Diario!$G$4:$G$203,Trato_Diario!$B$4:$B$203,D$5,Trato_Diario!$A$4:$A$203,$A18)=0),"",SUMIFS(Trato_Diario!$J$4:$J$203,Trato_Diario!$B$4:$B$203,D$5,Trato_Diario!$A$4:$A$203,$A18)/SUMIFS(Trato_Diario!$G$4:$G$203,Trato_Diario!$B$4:$B$203,D$5,Trato_Diario!$A$4:$A$203,$A18)) -> 6.0160909 | E18: =IF(OR($A18>MAX(Trato_Diario!$A$4:$A$203),SUMIFS(Trato_Diario!$G$4:$G$203,Trato_Diario!$B$4:$B$203,E$5,Trato_Diario!$A$4:$A$203,$A18)=0),"",SUMIFS(Trato_Diario!$J$4:$J$203,Trato_Diario!$B$4:$B$203,E$5,Trato_Diario!$A$4:$A$203,$A18)/SUMIFS(Trato_Diario!$G$4:$G$203,Trato_Diario!$B$4:$B$203,E$5,Trato_Diario!$A$4:$A$203,$A18)) -> 16.149483 | F18: =IF(OR($A18>MAX(Trato_Diario!$A$4:$A$203),SUMIFS(Trato_Diario!$G$4:$G$203,Trato_Diario!$B$4:$B$203,F$5,Trato_Diario!$A$4:$A$203,$A18)=0),"",SUMIFS(Trato_Diario!$J$4:$J$203,Trato_Diario!$B$4:$B$203,F$5,Trato_Diario!$A$4:$A$203,$A18)/SUMIFS(Trato_Diario!$G$4:$G$203,Trato_Diario!$B$4:$B$203,F$5,Trato_Diario!$A$4:$A$203,$A18)) | G18: =IF(OR($A18>MAX(Trato_Diario!$A$4:$A$203),SUMIFS(Trato_Diario!$G$4:$G$203,Trato_Diario!$B$4:$B$203,G$5,Trato_Diario!$A$4:$A$203,$A18)=0),"",SUMIFS(Trato_Diario!$J$4:$J$203,Trato_Diario!$B$4:$B$203,G$5,Trato_Diario!$A$4:$A$203,$A18)/SUMIFS(Trato_Diario!$G$4:$G$203,Trato_Diario!$B$4:$B$203,G$5,Trato_Diario!$A$4:$A$203,$A18)) | H18: =IF(OR($A18>MAX(Trato_Diario!$A$4:$A$203),SUMIFS(Trato_Diario!$G$4:$G$203,Trato_Diario!$A$4:$A$203,$A18)=0),"",SUMIFS(Trato_Diario!$J$4:$J$203,Trato_Diario!$A$4:$A$203,$A18)/SUMIFS(Trato_Diario!$G$4:$G$203,Trato_Diario!$A$4:$A$203,$A18)) -> 7.725018
A19: 46206 | B19: =IF(OR($A19>MAX(Trato_Diario!$A$4:$A$203),SUMIFS(Trato_Diario!$G$4:$G$203,Trato_Diario!$B$4:$B$203,B$5,Trato_Diario!$A$4:$A$203,$A19)=0),"",SUMIFS(Trato_Diario!$J$4:$J$203,Trato_Diario!$B$4:$B$203,B$5,Trato_Diario!$A$4:$A$203,$A19)/SUMIFS(Trato_Diario!$G$4:$G$203,Trato_Diario!$B$4:$B$203,B$5,Trato_Diario!$A$4:$A$203,$A19)) -> 10.8405 | C19: =IF(OR($A19>MAX(Trato_Diario!$A$4:$A$203),SUMIFS(Trato_Diario!$G$4:$G$203,Trato_Diario!$B$4:$B$203,C$5,Trato_Diario!$A$4:$A$203,$A19)=0),"",SUMIFS(Trato_Diario!$J$4:$J$203,Trato_Diario!$B$4:$B$203,C$5,Trato_Diario!$A$4:$A$203,$A19)/SUMIFS(Trato_Diario!$G$4:$G$203,Trato_Diario!$B$4:$B$203,C$5,Trato_Diario!$A$4:$A$203,$A19)) -> 7.9601739 | D19: =IF(OR($A19>MAX(Trato_Diario!$A$4:$A$203),SUMIFS(Trato_Diario!$G$4:$G$203,Trato_Diario!$B$4:$B$203,D$5,Trato_Diario!$A$4:$A$203,$A19)=0),"",SUMIFS(Trato_Diario!$J$4:$J$203,Trato_Diario!$B$4:$B$203,D$5,Trato_Diario!$A$4:$A$203,$A19)/SUMIFS(Trato_Diario!$G$4:$G$203,Trato_Diario!$B$4:$B$203,D$5,Trato_Diario!$A$4:$A$203,$A19)) -> 6.0160909 | E19: =IF(OR($A19>MAX(Trato_Diario!$A$4:$A$203),SUMIFS(Trato_Diario!$G$4:$G$203,Trato_Diario!$B$4:$B$203,E$5,Trato_Diario!$A$4:$A$203,$A19)=0),"",SUMIFS(Trato_Diario!$J$4:$J$203,Trato_Diario!$B$4:$B$203,E$5,Trato_Diario!$A$4:$A$203,$A19)/SUMIFS(Trato_Diario!$G$4:$G$203,Trato_Diario!$B$4:$B$203,E$5,Trato_Diario!$A$4:$A$203,$A19)) -> 16.149483 | F19: =IF(OR($A19>MAX(Trato_Diario!$A$4:$A$203),SUMIFS(Trato_Diario!$G$4:$G$203,Trato_Diario!$B$4:$B$203,F$5,Trato_Diario!$A$4:$A$203,$A19)=0),"",SUMIFS(Trato_Diario!$J$4:$J$203,Trato_Diario!$B$4:$B$203,F$5,Trato_Diario!$A$4:$A$203,$A19)/SUMIFS(Trato_Diario!$G$4:$G$203,Trato_Diario!$B$4:$B$203,F$5,Trato_Diario!$A$4:$A$203,$A19)) | G19: =IF(OR($A19>MAX(Trato_Diario!$A$4:$A$203),SUMIFS(Trato_Diario!$G$4:$G$203,Trato_Diario!$B$4:$B$203,G$5,Trato_Diario!$A$4:$A$203,$A19)=0),"",SUMIFS(Trato_Diario!$J$4:$J$203,Trato_Diario!$B$4:$B$203,G$5,Trato_Diario!$A$4:$A$203,$A19)/SUMIFS(Trato_Diario!$G$4:$G$203,Trato_Diario!$B$4:$B$203,G$5,Trato_Diario!$A$4:$A$203,$A19)) | H19: =IF(OR($A19>MAX(Trato_Diario!$A$4:$A$203),SUMIFS(Trato_Diario!$G$4:$G$203,Trato_Diario!$A$4:$A$203,$A19)=0),"",SUMIFS(Trato_Diario!$J$4:$J$203,Trato_Diario!$A$4:$A$203,$A19)/SUMIFS(Trato_Diario!$G$4:$G$203,Trato_Diario!$A$4:$A$203,$A19)) -> 8.0543058
A20: 46207 | B20: =IF(OR($A20>MAX(Trato_Diario!$A$4:$A$203),SUMIFS(Trato_Diario!$G$4:$G$203,Trato_Diario!$B$4:$B$203,B$5,Trato_Diario!$A$4:$A$203,$A20)=0),"",SUMIFS(Trato_Diario!$J$4:$J$203,Trato_Diario!$B$4:$B$203,B$5,Trato_Diario!$A$4:$A$203,$A20)/SUMIFS(Trato_Diario!$G$4:$G$203,Trato_Diario!$B$4:$B$203,B$5,Trato_Diario!$A$4:$A$203,$A20)) -> 10.8405 | C20: =IF(OR($A20>MAX(Trato_Diario!$A$4:$A$203),SUMIFS(Trato_Diario!$G$4:$G$203,Trato_Diario!$B$4:$B$203,C$5,Trato_Diario!$A$4:$A$203,$A20)=0),"",SUMIFS(Trato_Diario!$J$4:$J$203,Trato_Diario!$B$4:$B$203,C$5,Trato_Diario!$A$4:$A$203,$A20)/SUMIFS(Trato_Diario!$G$4:$G$203,Trato_Diario!$B$4:$B$203,C$5,Trato_Diario!$A$4:$A$203,$A20)) -> 7.9601739 | D20: =IF(OR($A20>MAX(Trato_Diario!$A$4:$A$203),SUMIFS(Trato_Diario!$G$4:$G$203,Trato_Diario!$B$4:$B$203,D$5,Trato_Diario!$A$4:$A$203,$A20)=0),"",SUMIFS(Trato_Diario!$J$4:$J$203,Trato_Diario!$B$4:$B$203,D$5,Trato_Diario!$A$4:$A$203,$A20)/SUMIFS(Trato_Diario!$G$4:$G$203,Trato_Diario!$B$4:$B$203,D$5,Trato_Diario!$A$4:$A$203,$A20)) -> 6.0160909 | E20: =IF(OR($A20>MAX(Trato_Diario!$A$4:$A$203),SUMIFS(Trato_Diario!$G$4:$G$203,Trato_Diario!$B$4:$B$203,E$5,Trato_Diario!$A$4:$A$203,$A20)=0),"",SUMIFS(Trato_Diario!$J$4:$J$203,Trato_Diario!$B$4:$B$203,E$5,Trato_Diario!$A$4:$A$203,$A20)/SUMIFS(Trato_Diario!$G$4:$G$203,Trato_Diario!$B$4:$B$203,E$5,Trato_Diario!$A$4:$A$203,$A20)) -> 16.149483 | F20: =IF(OR($A20>MAX(Trato_Diario!$A$4:$A$203),SUMIFS(Trato_Diario!$G$4:$G$203,Trato_Diario!$B$4:$B$203,F$5,Trato_Diario!$A$4:$A$203,$A20)=0),"",SUMIFS(Trato_Diario!$J$4:$J$203,Trato_Diario!$B$4:$B$203,F$5,Trato_Diario!$A$4:$A$203,$A20)/SUMIFS(Trato_Diario!$G$4:$G$203,Trato_Diario!$B$4:$B$203,F$5,Trato_Diario!$A$4:$A$203,$A20)) | G20: =IF(OR($A20>MAX(Trato_Diario!$A$4:$A$203),SUMIFS(Trato_Diario!$G$4:$G$203,Trato_Diario!$B$4:$B$203,G$5,Trato_Diario!$A$4:$A$203,$A20)=0),"",SUMIFS(Trato_Diario!$J$4:$J$203,Trato_Diario!$B$4:$B$203,G$5,Trato_Diario!$A$4:$A$203,$A20)/SUMIFS(Trato_Diario!$G$4:$G$203,Trato_Diario!$B$4:$B$203,G$5,Trato_Diario!$A$4:$A$203,$A20)) | H20: =IF(OR($A20>MAX(Trato_Diario!$A$4:$A$203),SUMIFS(Trato_Diario!$G$4:$G$203,Trato_Diario!$A$4:$A$203,$A20)=0),"",SUMIFS(Trato_Diario!$J$4:$J$203,Trato_Diario!$A$4:$A$203,$A20)/SUMIFS(Trato_Diario!$G$4:$G$203,Trato_Diario!$A$4:$A$203,$A20)) -> 8.0543058
A21: 46208 | B21: =IF(OR($A21>MAX(Trato_Diario!$A$4:$A$203),SUMIFS(Trato_Diario!$G$4:$G$203,Trato_Diario!$B$4:$B$203,B$5,Trato_Diario!$A$4:$A$203,$A21)=0),"",SUMIFS(Trato_Diario!$J$4:$J$203,Trato_Diario!$B$4:$B$203,B$5,Trato_Diario!$A$4:$A$203,$A21)/SUMIFS(Trato_Diario!$G$4:$G$203,Trato_Diario!$B$4:$B$203,B$5,Trato_Diario!$A$4:$A$203,$A21)) -> 10.8405 | C21: =IF(OR($A21>MAX(Trato_Diario!$A$4:$A$203),SUMIFS(Trato_Diario!$G$4:$G$203,Trato_Diario!$B$4:$B$203,C$5,Trato_Diario!$A$4:$A$203,$A21)=0),"",SUMIFS(Trato_Diario!$J$4:$J$203,Trato_Diario!$B$4:$B$203,C$5,Trato_Diario!$A$4:$A$203,$A21)/SUMIFS(Trato_Diario!$G$4:$G$203,Trato_Diario!$B$4:$B$203,C$5,Trato_Diario!$A$4:$A$203,$A21)) -> 7.9601739 | D21: =IF(OR($A21>MAX(Trato_Diario!$A$4:$A$203),SUMIFS(Trato_Diario!$G$4:$G$203,Trato_Diario!$B$4:$B$203,D$5,Trato_Diario!$A$4:$A$203,$A21)=0),"",SUMIFS(Trato_Diario!$J$4:$J$203,Trato_Diario!$B$4:$B$203,D$5,Trato_Diario!$A$4:$A$203,$A21)/SUMIFS(Trato_Diario!$G$4:$G$203,Trato_Diario!$B$4:$B$203,D$5,Trato_Diario!$A$4:$A$203,$A21)) -> 6.3327273 | E21: =IF(OR($A21>MAX(Trato_Diario!$A$4:$A$203),SUMIFS(Trato_Diario!$G$4:$G$203,Trato_Diario!$B$4:$B$203,E$5,Trato_Diario!$A$4:$A$203,$A21)=0),"",SUMIFS(Trato_Diario!$J$4:$J$203,Trato_Diario!$B$4:$B$203,E$5,Trato_Diario!$A$4:$A$203,$A21)/SUMIFS(Trato_Diario!$G$4:$G$203,Trato_Diario!$B$4:$B$203,E$5,Trato_Diario!$A$4:$A$203,$A21)) -> 16.149483 | F21: =IF(OR($A21>MAX(Trato_Diario!$A$4:$A$203),SUMIFS(Trato_Diario!$G$4:$G$203,Trato_Diario!$B$4:$B$203,F$5,Trato_Diario!$A$4:$A$203,$A21)=0),"",SUMIFS(Trato_Diario!$J$4:$J$203,Trato_Diario!$B$4:$B$203,F$5,Trato_Diario!$A$4:$A$203,$A21)/SUMIFS(Trato_Diario!$G$4:$G$203,Trato_Diario!$B$4:$B$203,F$5,Trato_Diario!$A$4:$A$203,$A21)) | G21: =IF(OR($A21>MAX(Trato_Diario!$A$4:$A$203),SUMIFS(Trato_Diario!$G$4:$G$203,Trato_Diario!$B$4:$B$203,G$5,Trato_Diario!$A$4:$A$203,$A21)=0),"",SUMIFS(Trato_Diario!$J$4:$J$203,Trato_Diario!$B$4:$B$203,G$5,Trato_Diario!$A$4:$A$203,$A21)/SUMIFS(Trato_Diario!$G$4:$G$203,Trato_Diario!$B$4:$B$203,G$5,Trato_Diario!$A$4:$A$203,$A21)) | H21: =IF(OR($A21>MAX(Trato_Diario!$A$4:$A$203),SUMIFS(Trato_Diario!$G$4:$G$203,Trato_Diario!$A$4:$A$203,$A21)=0),"",SUMIFS(Trato_Diario!$J$4:$J$203,Trato_Diario!$A$4:$A$203,$A21)/SUMIFS(Trato_Diario!$G$4:$G$203,Trato_Diario!$A$4:$A$203,$A21)) -> 8.2422374
A22: 46209 | B22: =IF(OR($A22>MAX(Trato_Diario!$A$4:$A$203),SUMIFS(Trato_Diario!$G$4:$G$203,Trato_Diario!$B$4:$B$203,B$5,Trato_Diario!$A$4:$A$203,$A22)=0),"",SUMIFS(Trato_Diario!$J$4:$J$203,Trato_Diario!$B$4:$B$203,B$5,Trato_Diario!$A$4:$A$203,$A22)/SUMIFS(Trato_Diario!$G$4:$G$203,Trato_Diario!$B$4:$B$203,B$5,Trato_Diario!$A$4:$A$203,$A22)) -> 12.045 | C22: =IF(OR($A22>MAX(Trato_Diario!$A$4:$A$203),SUMIFS(Trato_Diario!$G$4:$G$203,Trato_Diario!$B$4:$B$203,C$5,Trato_Diario!$A$4:$A$203,$A22)=0),"",SUMIFS(Trato_Diario!$J$4:$J$203,Trato_Diario!$B$4:$B$203,C$5,Trato_Diario!$A$4:$A$203,$A22)/SUMIFS(Trato_Diario!$G$4:$G$203,Trato_Diario!$B$4:$B$203,C$5,Trato_Diario!$A$4:$A$203,$A22)) -> 8.9551957 | D22: =IF(OR($A22>MAX(Trato_Diario!$A$4:$A$203),SUMIFS(Trato_Diario!$G$4:$G$203,Trato_Diario!$B$4:$B$203,D$5,Trato_Diario!$A$4:$A$203,$A22)=0),"",SUMIFS(Trato_Diario!$J$4:$J$203,Trato_Diario!$B$4:$B$203,D$5,Trato_Diario!$A$4:$A$203,$A22)/SUMIFS(Trato_Diario!$G$4:$G$203,Trato_Diario!$B$4:$B$203,D$5,Trato_Diario!$A$4:$A$203,$A22)) -> 6.3327273 | E22: =IF(OR($A22>MAX(Trato_Diario!$A$4:$A$203),SUMIFS(Trato_Diario!$G$4:$G$203,Trato_Diario!$B$4:$B$203,E$5,Trato_Diario!$A$4:$A$203,$A22)=0),"",SUMIFS(Trato_Diario!$J$4:$J$203,Trato_Diario!$B$4:$B$203,E$5,Trato_Diario!$A$4:$A$203,$A22)/SUMIFS(Trato_Diario!$G$4:$G$203,Trato_Diario!$B$4:$B$203,E$5,Trato_Diario!$A$4:$A$203,$A22)) -> 16.149483 | F22: =IF(OR($A22>MAX(Trato_Diario!$A$4:$A$203),SUMIFS(Trato_Diario!$G$4:$G$203,Trato_Diario!$B$4:$B$203,F$5,Trato_Diario!$A$4:$A$203,$A22)=0),"",SUMIFS(Trato_Diario!$J$4:$J$203,Trato_Diario!$B$4:$B$203,F$5,Trato_Diario!$A$4:$A$203,$A22)/SUMIFS(Trato_Diario!$G$4:$G$203,Trato_Diario!$B$4:$B$203,F$5,Trato_Diario!$A$4:$A$203,$A22)) | G22: =IF(OR($A22>MAX(Trato_Diario!$A$4:$A$203),SUMIFS(Trato_Diario!$G$4:$G$203,Trato_Diario!$B$4:$B$203,G$5,Trato_Diario!$A$4:$A$203,$A22)=0),"",SUMIFS(Trato_Diario!$J$4:$J$203,Trato_Diario!$B$4:$B$203,G$5,Trato_Diario!$A$4:$A$203,$A22)/SUMIFS(Trato_Diario!$G$4:$G$203,Trato_Diario!$B$4:$B$203,G$5,Trato_Diario!$A$4:$A$203,$A22)) | H22: =IF(OR($A22>MAX(Trato_Diario!$A$4:$A$203),SUMIFS(Trato_Diario!$G$4:$G$203,Trato_Diario!$A$4:$A$203,$A22)=0),"",SUMIFS(Trato_Diario!$J$4:$J$203,Trato_Diario!$A$4:$A$203,$A22)/SUMIFS(Trato_Diario!$G$4:$G$203,Trato_Diario!$A$4:$A$203,$A22)) -> 8.5715252
A23: 46210 | B23: =IF(OR($A23>MAX(Trato_Diario!$A$4:$A$203),SUMIFS(Trato_Diario!$G$4:$G$203,Trato_Diario!$B$4:$B$203,B$5,Trato_Diario!$A$4:$A$203,$A23)=0),"",SUMIFS(Trato_Diario!$J$4:$J$203,Trato_Diario!$B$4:$B$203,B$5,Trato_Diario!$A$4:$A$203,$A23)/SUMIFS(Trato_Diario!$G$4:$G$203,Trato_Diario!$B$4:$B$203,B$5,Trato_Diario!$A$4:$A$203,$A23)) -> 12.045 | C23: =IF(OR($A23>MAX(Trato_Diario!$A$4:$A$203),SUMIFS(Trato_Diario!$G$4:$G$203,Trato_Diario!$B$4:$B$203,C$5,Trato_Diario!$A$4:$A$203,$A23)=0),"",SUMIFS(Trato_Diario!$J$4:$J$203,Trato_Diario!$B$4:$B$203,C$5,Trato_Diario!$A$4:$A$203,$A23)/SUMIFS(Trato_Diario!$G$4:$G$203,Trato_Diario!$B$4:$B$203,C$5,Trato_Diario!$A$4:$A$203,$A23)) -> 8.9551957 | D23: =IF(OR($A23>MAX(Trato_Diario!$A$4:$A$203),SUMIFS(Trato_Diario!$G$4:$G$203,Trato_Diario!$B$4:$B$203,D$5,Trato_Diario!$A$4:$A$203,$A23)=0),"",SUMIFS(Trato_Diario!$J$4:$J$203,Trato_Diario!$B$4:$B$203,D$5,Trato_Diario!$A$4:$A$203,$A23)/SUMIFS(Trato_Diario!$G$4:$G$203,Trato_Diario!$B$4:$B$203,D$5,Trato_Diario!$A$4:$A$203,$A23)) -> 6.3327273 | E23: =IF(OR($A23>MAX(Trato_Diario!$A$4:$A$203),SUMIFS(Trato_Diario!$G$4:$G$203,Trato_Diario!$B$4:$B$203,E$5,Trato_Diario!$A$4:$A$203,$A23)=0),"",SUMIFS(Trato_Diario!$J$4:$J$203,Trato_Diario!$B$4:$B$203,E$5,Trato_Diario!$A$4:$A$203,$A23)/SUMIFS(Trato_Diario!$G$4:$G$203,Trato_Diario!$B$4:$B$203,E$5,Trato_Diario!$A$4:$A$203,$A23)) -> 16.149483 | F23: =IF(OR($A23>MAX(Trato_Diario!$A$4:$A$203),SUMIFS(Trato_Diario!$G$4:$G$203,Trato_Diario!$B$4:$B$203,F$5,Trato_Diario!$A$4:$A$203,$A23)=0),"",SUMIFS(Trato_Diario!$J$4:$J$203,Trato_Diario!$B$4:$B$203,F$5,Trato_Diario!$A$4:$A$203,$A23)/SUMIFS(Trato_Diario!$G$4:$G$203,Trato_Diario!$B$4:$B$203,F$5,Trato_Diario!$A$4:$A$203,$A23)) | G23: =IF(OR($A23>MAX(Trato_Diario!$A$4:$A$203),SUMIFS(Trato_Diario!$G$4:$G$203,Trato_Diario!$B$4:$B$203,G$5,Trato_Diario!$A$4:$A$203,$A23)=0),"",SUMIFS(Trato_Diario!$J$4:$J$203,Trato_Diario!$B$4:$B$203,G$5,Trato_Diario!$A$4:$A$203,$A23)/SUMIFS(Trato_Diario!$G$4:$G$203,Trato_Diario!$B$4:$B$203,G$5,Trato_Diario!$A$4:$A$203,$A23)) | H23: =IF(OR($A23>MAX(Trato_Diario!$A$4:$A$203),SUMIFS(Trato_Diario!$G$4:$G$203,Trato_Diario!$A$4:$A$203,$A23)=0),"",SUMIFS(Trato_Diario!$J$4:$J$203,Trato_Diario!$A$4:$A$203,$A23)/SUMIFS(Trato_Diario!$G$4:$G$203,Trato_Diario!$A$4:$A$203,$A23)) -> 8.5715252
... A201: 46388 | B201: =IF(OR($A201>MAX(Trato_Diario!$A$4:$A$203),SUMIFS(Trato_Diario!$G$4:$G$203,Trato_Diario!$B$4:$B$203,B$5,Trato_Diario!$A$4:$A$203,$A201)=0),"",SUMIFS(Trato_Diario!$J$4:$J$203,Trato_Diario!$B$4:$B$203,B$5,Trato_Diario!$A$4:$A$203,$A201)/SUMIFS(Trato_Diario!$G$4:$G$203,Trato_Diario!$B$4:$B$203,B$5,Trato_Diario!$A$4:$A$203,$A201)) | C201: =IF(OR($A201>MAX(Trato_Diario!$A$4:$A$203),SUMIFS(Trato_Diario!$G$4:$G$203,Trato_Diario!$B$4:$B$203,C$5,Trato_Diario!$A$4:$A$203,$A201)=0),"",SUMIFS(Trato_Diario!$J$4:$J$203,Trato_Diario!$B$4:$B$203,C$5,Trato_Diario!$A$4:$A$203,$A201)/SUMIFS(Trato_Diario!$G$4:$G$203,Trato_Diario!$B$4:$B$203,C$5,Trato_Diario!$A$4:$A$203,$A201)) | D201: =IF(OR($A201>MAX(Trato_Diario!$A$4:$A$203),SUMIFS(Trato_Diario!$G$4:$G$203,Trato_Diario!$B$4:$B$203,D$5,Trato_Diario!$A$4:$A$203,$A201)=0),"",SUMIFS(Trato_Diario!$J$4:$J$203,Trato_Diario!$B$4:$B$203,D$5,Trato_Diario!$A$4:$A$203,$A201)/SUMIFS(Trato_Diario!$G$4:$G$203,Trato_Diario!$B$4:$B$203,D$5,Trato_Diario!$A$4:$A$203,$A201)) | E201: =IF(OR($A201>MAX(Trato_Diario!$A$4:$A$203),SUMIFS(Trato_Diario!$G$4:$G$203,Trato_Diario!$B$4:$B$203,E$5,Trato_Diario!$A$4:$A$203,$A201)=0),"",SUMIFS(Trato_Diario!$J$4:$J$203,Trato_Diario!$B$4:$B$203,E$5,Trato_Diario!$A$4:$A$203,$A201)/SUMIFS(Trato_Diario!$G$4:$G$203,Trato_Diario!$B$4:$B$203,E$5,Trato_Diario!$A$4:$A$203,$A201)) | F201: =IF(OR($A201>MAX(Trato_Diario!$A$4:$A$203),SUMIFS(Trato_Diario!$G$4:$G$203,Trato_Diario!$B$4:$B$203,F$5,Trato_Diario!$A$4:$A$203,$A201)=0),"",SUMIFS(Trato_Diario!$J$4:$J$203,Trato_Diario!$B$4:$B$203,F$5,Trato_Diario!$A$4:$A$203,$A201)/SUMIFS(Trato_Diario!$G$4:$G$203,Trato_Diario!$B$4:$B$203,F$5,Trato_Diario!$A$4:$A$203,$A201)) | G201: =IF(OR($A201>MAX(Trato_Diario!$A$4:$A$203),SUMIFS(Trato_Diario!$G$4:$G$203,Trato_Diario!$B$4:$B$203,G$5,Trato_Diario!$A$4:$A$203,$A201)=0),"",SUMIFS(Trato_Diario!$J$4:$J$203,Trato_Diario!$B$4:$B$203,G$5,Trato_Diario!$A$4:$A$203,$A201)/SUMIFS(Trato_Diario!$G$4:$G$203,Trato_Diario!$B$4:$B$203,G$5,Trato_Diario!$A$4:$A$203,$A201)) | H201: =IF(OR($A201>MAX(Trato_Diario!$A$4:$A$203),SUMIFS(Trato_Diario!$G$4:$G$203,Trato_Diario!$A$4:$A$203,$A201)=0),"",SUMIFS(Trato_Diario!$J$4:$J$203,Trato_Diario!$A$4:$A$203,$A201)/SUMIFS(Trato_Diario!$G$4:$G$203,Trato_Diario!$A$4:$A$203,$A201))

Sheet Historico_KPIs
A1: HISTÓRICO DE KPIs — ZOOTÉCNICO E FINANCEIRO (BG)
A2: Para guardar um snapshot: selecione a linha AO VIVO (linha 4), copie e cole como VALORES na primeira linha vazia do histórico. Congela os KPIs daquela data.
A3: Data | B3: Nº Animais | C3: Peso Médio (kg) | D3: GMD Médio (kg/dia) | E3: @ em Estoque | F3: Ganho Acum. (kg) | G3: @ Produzidas | H3: Consumo/dia (kg MN) | I3: Custo Dieta médio (R$/kg) | J3: Custo Ração/dia (R$) | K3: Custo Ração/cab/dia (R$) | L3: Custo Estim./@ prod. (R$) | M3: Preço Arroba (R$/@) | N3: Valor Rebanho (R$) | O3: Obs
A4: =Parâmetros!$C$4 -> 46246 | B4: =COUNTA(Cadastro_Animais!$B$3:$B$5001) -> 385 | C4: =IFERROR(AVERAGE(Cadastro_Animais!$I$3:$I$5001),"") -> 348.91169 | D4: =IFERROR(AVERAGE(Cadastro_Animais!$L$3:$L$5001),"") -> 2.369628 | E4: =SUM(Cadastro_Animais!$M$3:$M$5001) -> 4746.362 | F4: =SUM(Cadastro_Animais!$K$3:$K$5001) -> 5995 | G4: =SUM(Cadastro_Animais!$N$3:$N$5001) -> 211.82333 | H4: =Calculadora_Trato!$I$14 -> 3223.944 | I4: =Parâmetros!$C$6 -> 0.54970799 | J4: =Calculadora_Trato!$N$14 -> 1772.2278 | K4: =IFERROR(Calculadora_Trato!$N$14/COUNTA(Cadastro_Animais!$B$3:$B$5001),"") -> 4.603189 | L4: =IF(Custo_Nutricao_Lote!$L$12<=0,"",Custo_Nutricao_Lote!$I$12/Custo_Nutricao_Lote!$L$12) -> 303.83857 | M4: =Parâmetros!$C$5 -> 310 | N4: =SUM(Cadastro_Animais!$O$3:$O$5001) -> 1471372.2 | O4: AO VIVO — não colar valores nesta linha
A6: HISTÓRICO (cole valores aqui, uma linha por data):
A7: Data | B7: Nº Animais | C7: Peso Médio (kg) | D7: GMD Médio (kg/dia) | E7: @ em Estoque | F7: Ganho Acum. (kg) | G7: @ Produzidas | H7: Consumo/dia (kg MN) | I7: Custo Dieta médio (R$/kg) | J7: Custo Ração/dia (R$) | K7: Custo Ração/cab/dia (R$) | L7: Custo Estim./@ prod. (R$) | M7: Preço Arroba (R$/@) | N7: Valor Rebanho (R$) | O7: Obs
A8: 46233 | B8: 385 | C8: 346.74286 | D8: 1.8780153 | E8: 4716.8587 | F8: 7376 | G8: 260.61867 | H8: 3203.904 | I8: 0.54896152 | J8: 1758.82 | K8: 4.5683637 | L8: 275.36318 | M8: 320 | N8: 1509394.8 | O8: Snapshot inicial (exemplo)

Sheet Cadastro_Animais
A1: CADASTRO DE ANIMAIS
A2: ID | B2: Brinco | C2: Categoria | D2: Lote/Origem | E2: Curral | F2: Data Entrada | G2: Peso Entrada (kg) | H2: Data Última Pesagem | I2: Peso Atual (kg) | J2: Dias Confinado | K2: Ganho Total (kg) | L2: GMD (kg/dia) | M2: @ Atual | N2: Ganho (@) | O2: Valor Atual (R$) | P2: Meta GMD?
A3: 1 | B3: 897/24 | C3: Touro Bonsmara | D3: Retiro 1 | E3: 2 | F3: 46203 | G3: 550 | H3: =IF(COUNTIFS(Pesagens!$B$3:$B$5001,$B3)=0,"",_xlfn.MAXIFS(Pesagens!$A$3:$A$5001,Pesagens!$B$3:$B$5001,$B3,Pesagens!$E$3:$E$5001,"<>")) -> 46203 | I3: =IF($H3="","",IFERROR(AVERAGEIFS(Pesagens!$E$3:$E$5001,Pesagens!$B$3:$B$5001,$B3,Pesagens!$A$3:$A$5001,$H3),"")) -> 550 | J3: =IF(F3="","",Parâmetros!$C$4-F3) -> 43 | K3: =IF(OR(I3="",G3=""),"",I3-G3) -> 0 | L3: =IF(OR(I3="",G3="",H3<=F3),"",(I3-G3)/(H3-F3)) | M3: =IF(I3="","",I3*Parâmetros!$C$8/15) -> 19.433333 | N3: =IF(K3="","",K3*Parâmetros!$C$8/15) -> 0 | O3: =IF(M3="","",M3*Parâmetros!$C$5) -> 6024.3333 | P3: =IF(L3="","",IF(L3>=Parâmetros!$C$10,"Sim","Não"))
A4: 2 | B4: 930/24 | C4: Touro Bonsmara | D4: Retiro 1 | E4: 2 | F4: 46203 | G4: 564 | H4: =IF(COUNTIFS(Pesagens!$B$3:$B$5001,$B4)=0,"",_xlfn.MAXIFS(Pesagens!$A$3:$A$5001,Pesagens!$B$3:$B$5001,$B4,Pesagens!$E$3:$E$5001,"<>")) -> 46203 | I4: =IF($H4="","",IFERROR(AVERAGEIFS(Pesagens!$E$3:$E$5001,Pesagens!$B$3:$B$5001,$B4,Pesagens!$A$3:$A$5001,$H4),"")) -> 564 | J4: =IF(F4="","",Parâmetros!$C$4-F4) -> 43 | K4: =IF(OR(I4="",G4=""),"",I4-G4) -> 0 | L4: =IF(OR(I4="",G4="",H4<=F4),"",(I4-G4)/(H4-F4)) | M4: =IF(I4="","",I4*Parâmetros!$C$8/15) -> 19.928 | N4: =IF(K4="","",K4*Parâmetros!$C$8/15) -> 0 | O4: =IF(M4="","",M4*Parâmetros!$C$5) -> 6177.68 | P4: =IF(L4="","",IF(L4>=Parâmetros!$C$10,"Sim","Não"))
A5: 3 | B5: 1615/24 | C5: Touro Bonsmara | D5: Retiro 1 | E5: 2 | F5: 46203 | G5: 516 | H5: =IF(COUNTIFS(Pesagens!$B$3:$B$5001,$B5)=0,"",_xlfn.MAXIFS(Pesagens!$A$3:$A$5001,Pesagens!$B$3:$B$5001,$B5,Pesagens!$E$3:$E$5001,"<>")) -> 46203 | I5: =IF($H5="","",IFERROR(AVERAGEIFS(Pesagens!$E$3:$E$5001,Pesagens!$B$3:$B$5001,$B5,Pesagens!$A$3:$A$5001,$H5),"")) -> 516 | J5: =IF(F5="","",Parâmetros!$C$4-F5) -> 43 | K5: =IF(OR(I5="",G5=""),"",I5-G5) -> 0 | L5: =IF(OR(I5="",G5="",H5<=F5),"",(I5-G5)/(H5-F5)) | M5: =IF(I5="","",I5*Parâmetros!$C$8/15) -> 18.232 | N5: =IF(K5="","",K5*Parâmetros!$C$8/15) -> 0 | O5: =IF(M5="","",M5*Parâmetros!$C$5) -> 5651.92 | P5: =IF(L5="","",IF(L5>=Parâmetros!$C$10,"Sim","Não"))
A6: 4 | B6: 1769/24 | C6: Touro Bonsmara | D6: Retiro 1 | E6: 2 | F6: 46203 | G6: 533 | H6: =IF(COUNTIFS(Pesagens!$B$3:$B$5001,$B6)=0,"",_xlfn.MAXIFS(Pesagens!$A$3:$A$5001,Pesagens!$B$3:$B$5001,$B6,Pesagens!$E$3:$E$5001,"<>")) -> 46203 | I6: =IF($H6="","",IFERROR(AVERAGEIFS(Pesagens!$E$3:$E$5001,Pesagens!$B$3:$B$5001,$B6,Pesagens!$A$3:$A$5001,$H6),"")) -> 533 | J6: =IF(F6="","",Parâmetros!$C$4-F6) -> 43 | K6: =IF(OR(I6="",G6=""),"",I6-G6) -> 0 | L6: =IF(OR(I6="",G6="",H6<=F6),"",(I6-G6)/(H6-F6)) | M6: =IF(I6="","",I6*Parâmetros!$C$8/15) -> 18.832667 | N6: =IF(K6="","",K6*Parâmetros!$C$8/15) -> 0 | O6: =IF(M6="","",M6*Parâmetros!$C$5) -> 5838.1267 | P6: =IF(L6="","",IF(L6>=Parâmetros!$C$10,"Sim","Não"))
A7: 5 | B7: 1804/24 | C7: Touro Bonsmara | D7: Retiro 1 | E7: 2 | F7: 46203 | G7: 586 | H7: =IF(COUNTIFS(Pesagens!$B$3:$B$5001,$B7)=0,"",_xlfn.MAXIFS(Pesagens!$A$3:$A$5001,Pesagens!$B$3:$B$5001,$B7,Pesagens!$E$3:$E$5001,"<>")) -> 46203 | I7: =IF($H7="","",IFERROR(AVERAGEIFS(Pesagens!$E$3:$E$5001,Pesagens!$B$3:$B$5001,$B7,Pesagens!$A$3:$A$5001,$H7),"")) -> 586 | J7: =IF(F7="","",Parâmetros!$C$4-F7) -> 43 | K7: =IF(OR(I7="",G7=""),"",I7-G7) -> 0 | L7: =IF(OR(I7="",G7="",H7<=F7),"",(I7-G7)/(H7-F7)) | M7: =IF(I7="","",I7*Parâmetros!$C$8/15) -> 20.705333 | N7: =IF(K7="","",K7*Parâmetros!$C$8/15) -> 0 | O7: =IF(M7="","",M7*Parâmetros!$C$5) -> 6418.6533 | P7: =IF(L7="","",IF(L7>=Parâmetros!$C$10,"Sim","Não"))
A8: 6 | B8: 1815/24 | C8: Touro Bonsmara | D8: Retiro 1 | E8: 2 | F8: 46203 | G8: 553 | H8: =IF(COUNTIFS(Pesagens!$B$3:$B$5001,$B8)=0,"",_xlfn.MAXIFS(Pesagens!$A$3:$A$5001,Pesagens!$B$3:$B$5001,$B8,Pesagens!$E$3:$E$5001,"<>")) -> 46203 | I8: =IF($H8="","",IFERROR(AVERAGEIFS(Pesagens!$E$3:$E$5001,Pesagens!$B$3:$B$5001,$B8,Pesagens!$A$3:$A$5001,$H8),"")) -> 553 | J8: =IF(F8="","",Parâmetros!$C$4-F8) -> 43 | K8: =IF(OR(I8="",G8=""),"",I8-G8) -> 0 | L8: =IF(OR(I8="",G8="",H8<=F8),"",(I8-G8)/(H8-F8)) | M8: =IF(I8="","",I8*Parâmetros!$C$8/15) -> 19.539333 | N8: =IF(K8="","",K8*Parâmetros!$C$8/15) -> 0 | O8: =IF(M8="","",M8*Parâmetros!$C$5) -> 6057.1933 | P8: =IF(L8="","",IF(L8>=Parâmetros!$C$10,"Sim","Não"))
A9: 7 | B9: 1892/24 | C9: Touro Bonsmara | D9: Retiro 1 | E9: 2 | F9: 46203 | G9: 566 | H9: =IF(COUNTIFS(Pesagens!$B$3:$B$5001,$B9)=0,"",_xlfn.MAXIFS(Pesagens!$A$3:$A$5001,Pesagens!$B$3:$B$5001,$B9,Pesagens!$E$3:$E$5001,"<>")) -> 46203 | I9: =IF($H9="","",IFERROR(AVERAGEIFS(Pesagens!$E$3:$E$5001,Pesagens!$B$3:$B$5001,$B9,Pesagens!$A$3:$A$5001,$H9),"")) -> 566 | J9: =IF(F9="","",Parâmetros!$C$4-F9) -> 43 | K9: =IF(OR(I9="",G9=""),"",I9-G9) -> 0 | L9: =IF(OR(I9="",G9="",H9<=F9),"",(I9-G9)/(H9-F9)) | M9: =IF(I9="","",I9*Parâmetros!$C$8/15) -> 19.998667 | N9: =IF(K9="","",K9*Parâmetros!$C$8/15) -> 0 | O9: =IF(M9="","",M9*Parâmetros!$C$5) -> 6199.5867 | P9: =IF(L9="","",IF(L9>=Parâmetros!$C$10,"Sim","Não"))
A10: 8 | B10: 2004/24 | C10: Touro Bonsmara | D10: Retiro 1 | E10: 2 | F10: 46203 | G10: 518 | H10: =IF(COUNTIFS(Pesagens!$B$3:$B$5001,$B10)=0,"",_xlfn.MAXIFS(Pesagens!$A$3:$A$5001,Pesagens!$B$3:$B$5001,$B10,Pesagens!$E$3:$E$5001,"<>")) -> 46203 | I10: =IF($H10="","",IFERROR(AVERAGEIFS(Pesagens!$E$3:$E$5001,Pesagens!$B$3:$B$5001,$B10,Pesagens!$A$3:$A$5001,$H10),"")) -> 518 | J10: =IF(F10="","",Parâmetros!$C$4-F10) -> 43 | K10: =IF(OR(I10="",G10=""),"",I10-G10) -> 0 | L10: =IF(OR(I10="",G10="",H10<=F10),"",(I10-G10)/(H10-F10)) | M10: =IF(I10="","",I10*Parâmetros!$C$8/15) -> 18.302667 | N10: =IF(K10="","",K10*Parâmetros!$C$8/15) -> 0 | O10: =IF(M10="","",M10*Parâmetros!$C$5) -> 5673.8267 | P10: =IF(L10="","",IF(L10>=Parâmetros!$C$10,"Sim","Não"))
A11: 9 | B11: BBG 3339 | C11: Touro Bonsmara | D11: Retiro 1 | E11: 2 | F11: 46203 | G11: 670 | H11: =IF(COUNTIFS(Pesagens!$B$3:$B$5001,$B11)=0,"",_xlfn.MAXIFS(Pesagens!$A$3:$A$5001,Pesagens!$B$3:$B$5001,$B11,Pesagens!$E$3:$E$5001,"<>")) -> 46203 | I11: =IF($H11="","",IFERROR(AVERAGEIFS(Pesagens!$E$3:$E$5001,Pesagens!$B$3:$B$5001,$B11,Pesagens!$A$3:$A$5001,$H11),"")) -> 670 | J11: =IF(F11="","",Parâmetros!$C$4-F11) -> 43 | K11: =IF(OR(I11="",G11=""),"",I11-G11) -> 0 | L11: =IF(OR(I11="",G11="",H11<=F11),"",(I11-G11)/(H11-F11)) | M11: =IF(I11="","",I11*Parâmetros!$C$8/15) -> 23.673333 | N11: =IF(K11="","",K11*Parâmetros!$C$8/15) -> 0 | O11: =IF(M11="","",M11*Parâmetros!$C$5) -> 7338.7333 | P11: =IF(L11="","",IF(L11>=Parâmetros!$C$10,"Sim","Não"))
A12: 10 | B12: BBG 3356 | C12: Touro Bonsmara | D12: Retiro 1 | E12: 2 | F12: 46203 | G12: 577 | H12: =IF(COUNTIFS(Pesagens!$B$3:$B$5001,$B12)=0,"",_xlfn.MAXIFS(Pesagens!$A$3:$A$5001,Pesagens!$B$3:$B$5001,$B12,Pesagens!$E$3:$E$5001,"<>")) -> 46203 | I12: =IF($H12="","",IFERROR(AVERAGEIFS(Pesagens!$E$3:$E$5001,Pesagens!$B$3:$B$5001,$B12,Pesagens!$A$3:$A$5001,$H12),"")) -> 577 | J12: =IF(F12="","",Parâmetros!$C$4-F12) -> 43 | K12: =IF(OR(I12="",G12=""),"",I12-G12) -> 0 | L12: =IF(OR(I12="",G12="",H12<=F12),"",(I12-G12)/(H12-F12)) | M12: =IF(I12="","",I12*Parâmetros!$C$8/15) -> 20.387333 | N12: =IF(K12="","",K12*Parâmetros!$C$8/15) -> 0 | O12: =IF(M12="","",M12*Parâmetros!$C$5) -> 6320.0733 | P12: =IF(L12="","",IF(L12>=Parâmetros!$C$10,"Sim","Não"))
A13: 11 | B13: BBG 3358 | C13: Touro Bonsmara | D13: Retiro 1 | E13: 2 | F13: 46203 | G13: 548 | H13: =IF(COUNTIFS(Pesagens!$B$3:$B$5001,$B13)=0,"",_xlfn.MAXIFS(Pesagens!$A$3:$A$5001,Pesagens!$B$3:$B$5001,$B13,Pesagens!$E$3:$E$5001,"<>")) -> 46203 | I13: =IF($H13="","",IFERROR(AVERAGEIFS(Pesagens!$E$3:$E$5001,Pesagens!$B$3:$B$5001,$B13,Pesagens!$A$3:$A$5001,$H13),"")) -> 548 | J13: =IF(F13="","",Parâmetros!$C$4-F13) -> 43 | K13: =IF(OR(I13="",G13=""),"",I13-G13) -> 0 | L13: =IF(OR(I13="",G13="",H13<=F13),"",(I13-G13)/(H13-F13)) | M13: =IF(I13="","",I13*Parâmetros!$C$8/15) -> 19.362667 | N13: =IF(K13="","",K13*Parâmetros!$C$8/15) -> 0 | O13: =IF(M13="","",M13*Parâmetros!$C$5) -> 6002.4267 | P13: =IF(L13="","",IF(L13>=Parâmetros!$C$10,"Sim","Não"))
A14: 12 | B14: BBG 3359 | C14: Touro Bonsmara | D14: Retiro 1 | E14: 2 | F14: 46203 | G14: 508 | H14: =IF(COUNTIFS(Pesagens!$B$3:$B$5001,$B14)=0,"",_xlfn.MAXIFS(Pesagens!$A$3:$A$5001,Pesagens!$B$3:$B$5001,$B14,Pesagens!$E$3:$E$5001,"<>")) -> 46203 | I14: =IF($H14="","",IFERROR(AVERAGEIFS(Pesagens!$E$3:$E$5001,Pesagens!$B$3:$B$5001,$B14,Pesagens!$A$3:$A$5001,$H14),"")) -> 508 | J14: =IF(F14="","",Parâmetros!$C$4-F14) -> 43 | K14: =IF(OR(I14="",G14=""),"",I14-G14) -> 0 | L14: =IF(OR(I14="",G14="",H14<=F14),"",(I14-G14)/(H14-F14)) | M14: =IF(I14="","",I14*Parâmetros!$C$8/15) -> 17.949333 | N14: =IF(K14="","",K14*Parâmetros!$C$8/15) -> 0 | O14: =IF(M14="","",M14*Parâmetros!$C$5) -> 5564.2933 | P14: =IF(L14="","",IF(L14>=Parâmetros!$C$10,"Sim","Não"))
... A107: 105 | B107: 2394 | C107: Touro Nelore | D107: Lote 04 | E107: 4-TN | F107: 46203 | G107: 443 | H107: =IF(COUNTIFS(Pesagens!$B$3:$B$5001,$B107)=0,"",_xlfn.MAXIFS(Pesagens!$A$3:$A$5001,Pesagens!$B$3:$B$5001,$B107,Pesagens!$E$3:$E$5001,"<>")) -> 46246 | I107: =IF($H107="","",IFERROR(AVERAGEIFS(Pesagens!$E$3:$E$5001,Pesagens!$B$3:$B$5001,$B107,Pesagens!$A$3:$A$5001,$H107),"")) -> 547 | J107: =IF(F107="","",Parâmetros!$C$4-F107) -> 43 | K107: =IF(OR(I107="",G107=""),"",I107-G107) -> 104 | L107: =IF(OR(I107="",G107="",H107<=F107),"",(I107-G107)/(H107-F107)) -> 2.4186047 | M107: =IF(I107="","",I107*Parâmetros!$C$8/15) -> 19.327333 | N107: =IF(K107="","",K107*Parâmetros!$C$8/15) -> 3.6746667 | O107: =IF(M107="","",M107*Parâmetros!$C$5) -> 5991.4733 | P107: =IF(L107="","",IF(L107>=Parâmetros!$C$10,"Sim","Não")) -> Sim
A108: 106 | B108: 2307 | C108: Touro Nelore | D108: Lote 04 | E108: 4-TN | F108: 46233 | G108: 577 | H108: =IF(COUNTIFS(Pesagens!$B$3:$B$5001,$B108)=0,"",_xlfn.MAXIFS(Pesagens!$A$3:$A$5001,Pesagens!$B$3:$B$5001,$B108,Pesagens!$E$3:$E$5001,"<>")) -> 46246 | I108: =IF($H108="","",IFERROR(AVERAGEIFS(Pesagens!$E$3:$E$5001,Pesagens!$B$3:$B$5001,$B108,Pesagens!$A$3:$A$5001,$H108),"")) -> 610 | J108: =IF(F108="","",Parâmetros!$C$4-F108) -> 13 | K108: =IF(OR(I108="",G108=""),"",I108-G108) -> 33 | L108: =IF(OR(I108="",G108="",H108<=F108),"",(I108-G108)/(H108-F108)) -> 2.5384615 | M108: =IF(I108="","",I108*Parâmetros!$C$8/15) -> 21.553333 | N108: =IF(K108="","",K108*Parâmetros!$C$8/15) -> 1.166 | O108: =IF(M108="","",M108*Parâmetros!$C$5) -> 6681.5333 | P108: =IF(L108="","",IF(L108>=Parâmetros!$C$10,"Sim","Não")) -> Sim
A109: 107 | B109: 2265 | C109: Touro Nelore | D109: Lote 04 | E109: 4-TN | F109: 46203 | G109: 437 | H109: =IF(COUNTIFS(Pesagens!$B$3:$B$5001,$B109)=0,"",_xlfn.MAXIFS(Pesagens!$A$3:$A$5001,Pesagens!$B$3:$B$5001,$B109,Pesagens!$E$3:$E$5001,"<>")) -> 46246 | I109: =IF($H109="","",IFERROR(AVERAGEIFS(Pesagens!$E$3:$E$5001,Pesagens!$B$3:$B$5001,$B109,Pesagens!$A$3:$A$5001,$H109),"")) -> 520 | J109: =IF(F109="","",Parâmetros!$C$4-F109) -> 43 | K109: =IF(OR(I109="",G109=""),"",I109-G109) -> 83 | L109: =IF(OR(I109="",G109="",H109<=F109),"",(I109-G109)/(H109-F109)) -> 1.9302326 | M109: =IF(I109="","",I109*Parâmetros!$C$8/15) -> 18.373333 | N109: =IF(K109="","",K109*Parâmetros!$C$8/15) -> 2.9326667 | O109: =IF(M109="","",M109*Parâmetros!$C$5) -> 5695.7333 | P109: =IF(L109="","",IF(L109>=Parâmetros!$C$10,"Sim","Não")) -> Sim
A110: 108 | B110: 2298 | C110: Touro Nelore | D110: Lote 04 | E110: 4-TN | F110: 46203 | G110: 437 | H110: =IF(COUNTIFS(Pesagens!$B$3:$B$5001,$B110)=0,"",_xlfn.MAXIFS(Pesagens!$A$3:$A$5001,Pesagens!$B$3:$B$5001,$B110,Pesagens!$E$3:$E$5001,"<>")) -> 46246 | I110: =IF($H110="","",IFERROR(AVERAGEIFS(Pesagens!$E$3:$E$5001,Pesagens!$B$3:$B$5001,$B110,Pesagens!$A$3:$A$5001,$H110),"")) -> 522 | J110: =IF(F110="","",Parâmetros!$C$4-F110) -> 43 | K110: =IF(OR(I110="",G110=""),"",I110-G110) -> 85 | L110: =IF(OR(I110="",G110="",H110<=F110),"",(I110-G110)/(H110-F110)) -> 1.9767442 | M110: =IF(I110="","",I110*Parâmetros!$C$8/15) -> 18.444 | N110: =IF(K110="","",K110*Parâmetros!$C$8/15) -> 3.0033333 | O110: =IF(M110="","",M110*Parâmetros!$C$5) -> 5717.64 | P110: =IF(L110="","",IF(L110>=Parâmetros!$C$10,"Sim","Não")) -> Sim
A111: 109 | B111: 2388 | C111: Touro Nelore | D111: Lote 04 | E111: 4-TN | F111: 46203 | G111: 437 | H111: =IF(COUNTIFS(Pesagens!$B$3:$B$5001,$B111)=0,"",_xlfn.MAXIFS(Pesagens!$A$3:$A$5001,Pesagens!$B$3:$B$5001,$B111,Pesagens!$E$3:$E$5001,"<>")) -> 46246 | I111: =IF($H111="","",IFERROR(AVERAGEIFS(Pesagens!$E$3:$E$5001,Pesagens!$B$3:$B$5001,$B111,Pesagens!$A$3:$A$5001,$H111),"")) -> 516 | J111: =IF(F111="","",Parâmetros!$C$4-F111) -> 43 | K111: =IF(OR(I111="",G111=""),"",I111-G111) -> 79 | L111: =IF(OR(I111="",G111="",H111<=F111),"",(I111-G111)/(H111-F111)) -> 1.8372093 | M111: =IF(I111="","",I111*Parâmetros!$C$8/15) -> 18.232 | N111: =IF(K111="","",K111*Parâmetros!$C$8/15) -> 2.7913333 | O111: =IF(M111="","",M111*Parâmetros!$C$5) -> 5651.92 | P111: =IF(L111="","",IF(L111>=Parâmetros!$C$10,"Sim","Não")) -> Sim
A112: 110 | B112: 2277 | C112: Touro Nelore | D112: Lote 04 | E112: 4-TN | F112: 46203 | G112: 431 | H112: =IF(COUNTIFS(Pesagens!$B$3:$B$5001,$B112)=0,"",_xlfn.MAXIFS(Pesagens!$A$3:$A$5001,Pesagens!$B$3:$B$5001,$B112,Pesagens!$E$3:$E$5001,"<>")) -> 46246 | I112: =IF($H112="","",IFERROR(AVERAGEIFS(Pesagens!$E$3:$E$5001,Pesagens!$B$3:$B$5001,$B112,Pesagens!$A$3:$A$5001,$H112),"")) -> 525 | J112: =IF(F112="","",Parâmetros!$C$4-F112) -> 43 | K112: =IF(OR(I112="",G112=""),"",I112-G112) -> 94 | L112: =IF(OR(I112="",G112="",H112<=F112),"",(I112-G112)/(H112-F112)) -> 2.1860465 | M112: =IF(I112="","",I112*Parâmetros!$C$8/15) -> 18.55 | N112: =IF(K112="","",K112*Parâmetros!$C$8/15) -> 3.3213333 | O112: =IF(M112="","",M112*Parâmetros!$C$5) -> 5750.5 | P112: =IF(L112="","",IF(L112>=Parâmetros!$C$10,"Sim","Não")) -> Sim
A113: 111 | B113: 2406 | C113: Touro Nelore | D113: Lote 04 | E113: 4-TN | F113: 46203 | G113: 427 | H113: =IF(COUNTIFS(Pesagens!$B$3:$B$5001,$B113)=0,"",_xlfn.MAXIFS(Pesagens!$A$3:$A$5001,Pesagens!$B$3:$B$5001,$B113,Pesagens!$E$3:$E$5001,"<>")) -> 46246 | I113: =IF($H113="","",IFERROR(AVERAGEIFS(Pesagens!$E$3:$E$5001,Pesagens!$B$3:$B$5001,$B113,Pesagens!$A$3:$A$5001,$H113),"")) -> 530 | J113: =IF(F113="","",Parâmetros!$C$4-F113) -> 43 | K113: =IF(OR(I113="",G113=""),"",I113-G113) -> 103 | L113: =IF(OR(I113="",G113="",H113<=F113),"",(I113-G113)/(H113-F113)) -> 2.3953488 | M113: =IF(I113="","",I113*Parâmetros!$C$8/15) -> 18.726667 | N113: =IF(K113="","",K113*Parâmetros!$C$8/15) -> 3.6393333 | O113: =IF(M113="","",M113*Parâmetros!$C$5) -> 5805.2667 | P113: =IF(L113="","",IF(L113>=Parâmetros!$C$10,"Sim","Não")) -> Sim
A114: 112 | B114: 2365 | C114: Touro Nelore | D114: Lote 04 | E114: 4-TN | F114: 46203 | G114: 422 | H114: =IF(COUNTIFS(Pesagens!$B$3:$B$5001,$B114)=0,"",_xlfn.MAXIFS(Pesagens!$A$3:$A$5001,Pesagens!$B$3:$B$5001,$B114,Pesagens!$E$3:$E$5001,"<>")) -> 46246 | I114: =IF($H114="","",IFERROR(AVERAGEIFS(Pesagens!$E$3:$E$5001,Pesagens!$B$3:$B$5001,$B114,Pesagens!$A$3:$A$5001,$H114),"")) -> 526 | J114: =IF(F114="","",Parâmetros!$C$4-F114) -> 43 | K114: =IF(OR(I114="",G114=""),"",I114-G114) -> 104 | L114: =IF(OR(I114="",G114="",H114<=F114),"",(I114-G114)/(H114-F114)) -> 2.4186047 | M114: =IF(I114="","",I114*Parâmetros!$C$8/15) -> 18.585333 | N114: =IF(K114="","",K114*Parâmetros!$C$8/15) -> 3.6746667 | O114: =IF(M114="","",M114*Parâmetros!$C$5) -> 5761.4533 | P114: =IF(L114="","",IF(L114>=Parâmetros!$C$10,"Sim","Não")) -> Sim
A115: 113 | B115: 2410 | C115: Touro Nelore | D115: Lote 04 | E115: 4-TN | F115: 46203 | G115: 409 | H115: =IF(COUNTIFS(Pesagens!$B$3:$B$5001,$B115)=0,"",_xlfn.MAXIFS(Pesagens!$A$3:$A$5001,Pesagens!$B$3:$B$5001,$B115,Pesagens!$E$3:$E$5001,"<>")) -> 46246 | I115: =IF($H115="","",IFERROR(AVERAGEIFS(Pesagens!$E$3:$E$5001,Pesagens!$B$3:$B$5001,$B115,Pesagens!$A$3:$A$5001,$H115),"")) -> 491 | J115: =IF(F115="","",Parâmetros!$C$4-F115) -> 43 | K115: =IF(OR(I115="",G115=""),"",I115-G115) -> 82 | L115: =IF(OR(I115="",G115="",H115<=F115),"",(I115-G115)/(H115-F115)) -> 1.9069767 | M115: =IF(I115="","",I115*Parâmetros!$C$8/15) -> 17.348667 | N115: =IF(K115="","",K115*Parâmetros!$C$8/15) -> 2.8973333 | O115: =IF(M115="","",M115*Parâmetros!$C$5) -> 5378.0867 | P115: =IF(L115="","",IF(L115>=Parâmetros!$C$10,"Sim","Não")) -> Sim
A116: 114 | B116: 1403/25 | C116: Bezerro | D116: Desmama BG | E116: 4 | F116: 46204 | G116: 305 | H116: =IF(COUNTIFS(Pesagens!$B$3:$B$5001,$B116)=0,"",_xlfn.MAXIFS(Pesagens!$A$3:$A$5001,Pesagens!$B$3:$B$5001,$B116,Pesagens!$E$3:$E$5001,"<>")) -> 46204 | I116: =IF($H116="","",IFERROR(AVERAGEIFS(Pesagens!$E$3:$E$5001,Pesagens!$B$3:$B$5001,$B116,Pesagens!$A$3:$A$5001,$H116),"")) -> 305 | J116: =IF(F116="","",Parâmetros!$C$4-F116) -> 42 | K116: =IF(OR(I116="",G116=""),"",I116-G116) -> 0 | L116: =IF(OR(I116="",G116="",H116<=F116),"",(I116-G116)/(H116-F116)) | M116: =IF(I116="","",I116*Parâmetros!$C$8/15) -> 10.776667 | N116: =IF(K116="","",K116*Parâmetros!$C$8/15) -> 0 | O116: =IF(M116="","",M116*Parâmetros!$C$5) -> 3340.7667 | P116: =IF(L116="","",IF(L116>=Parâmetros!$C$10,"Sim","Não"))
A117: 115 | B117: 2030/25 | C117: Bezerro | D117: Desmama BG | E117: 4 | F117: 46204 | G117: 297 | H117: =IF(COUNTIFS(Pesagens!$B$3:$B$5001,$B117)=0,"",_xlfn.MAXIFS(Pesagens!$A$3:$A$5001,Pesagens!$B$3:$B$5001,$B117,Pesagens!$E$3:$E$5001,"<>")) -> 46204 | I117: =IF($H117="","",IFERROR(AVERAGEIFS(Pesagens!$E$3:$E$5001,Pesagens!$B$3:$B$5001,$B117,Pesagens!$A$3:$A$5001,$H117),"")) -> 297 | J117: =IF(F117="","",Parâmetros!$C$4-F117) -> 42 | K117: =IF(OR(I117="",G117=""),"",I117-G117) -> 0 | L117: =IF(OR(I117="",G117="",H117<=F117),"",(I117-G117)/(H117-F117)) | M117: =IF(I117="","",I117*Parâmetros!$C$8/15) -> 10.494 | N117: =IF(K117="","",K117*Parâmetros!$C$8/15) -> 0 | O117: =IF(M117="","",M117*Parâmetros!$C$5) -> 3253.14 | P117: =IF(L117="","",IF(L117>=Parâmetros!$C$10,"Sim","Não"))
A118: 116 | B118: 2518 | C118: Bezerro | D118: Desmama BG | E118: 4 | F118: 46199 | G118: 243 | H118: =IF(COUNTIFS(Pesagens!$B$3:$B$5001,$B118)=0,"",_xlfn.MAXIFS(Pesagens!$A$3:$A$5001,Pesagens!$B$3:$B$5001,$B118,Pesagens!$E$3:$E$5001,"<>")) -> 46199 | I118: =IF($H118="","",IFERROR(AVERAGEIFS(Pesagens!$E$3:$E$5001,Pesagens!$B$3:$B$5001,$B118,Pesagens!$A$3:$A$5001,$H118),"")) -> 243 | J118: =IF(F118="","",Parâmetros!$C$4-F118) -> 47 | K118: =IF(OR(I118="",G118=""),"",I118-G118) -> 0 | L118: =IF(OR(I118="",G118="",H118<=F118),"",(I118-G118)/(H118-F118)) | M118: =IF(I118="","",I118*Parâmetros!$C$8/15) -> 8.586 | N118: =IF(K118="","",K118*Parâmetros!$C$8/15) -> 0 | O118: =IF(M118="","",M118*Parâmetros!$C$5) -> 2661.66 | P118: =IF(L118="","",IF(L118>=Parâmetros!$C$10,"Sim","Não"))
A119: 117 | B119: 3512 | C119: Bezerro | D119: Desmama BG | E119: 4 | F119: 46204 | G119: 254 | H119: =IF(COUNTIFS(Pesagens!$B$3:$B$5001,$B119)=0,"",_xlfn.MAXIFS(Pesagens!$A$3:$A$5001,Pesagens!$B$3:$B$5001,$B119,Pesagens!$E$3:$E$5001,"<>")) -> 46204 | I119: =IF($H119="","",IFERROR(AVERAGEIFS(Pesagens!$E$3:$E$5001,Pesagens!$B$3:$B$5001,$B119,Pesagens!$A$3:$A$5001,$H119),"")) -> 254 | J119: =IF(F119="","",Parâmetros!$C$4-F119) -> 42 | K119: =IF(OR(I119="",G119=""),"",I119-G119) -> 0 | L119: =IF(OR(I119="",G119="",H119<=F119),"",(I119-G119)/(H119-F119)) | M119: =IF(I119="","",I119*Parâmetros!$C$8/15) -> 8.9746667 | N119: =IF(K119="","",K119*Parâmetros!$C$8/15) -> 0 | O119: =IF(M119="","",M119*Parâmetros!$C$5) -> 2782.1467 | P119: =IF(L119="","",IF(L119>=Parâmetros!$C$10,"Sim","Não"))
A120: 118 | B120: 3513 | C120: Bezerro | D120: Desmama BG | E120: 4 | F120: 46204 | G120: 236 | H120: =IF(COUNTIFS(Pesagens!$B$3:$B$5001,$B120)=0,"",_xlfn.MAXIFS(Pesagens!$A$3:$A$5001,Pesagens!$B$3:$B$5001,$B120,Pesagens!$E$3:$E$5001,"<>")) -> 46204 | I120: =IF($H120="","",IFERROR(AVERAGEIFS(Pesagens!$E$3:$E$5001,Pesagens!$B$3:$B$5001,$B120,Pesagens!$A$3:$A$5001,$H120),"")) -> 236 | J120: =IF(F120="","",Parâmetros!$C$4-F120) -> 42 | K120: =IF(OR(I120="",G120=""),"",I120-G120) -> 0 | L120: =IF(OR(I120="",G120="",H120<=F120),"",(I120-G120)/(H120-F120)) | M120: =IF(I120="","",I120*Parâmetros!$C$8/15) -> 8.3386667 | N120: =IF(K120="","",K120*Parâmetros!$C$8/15) -> 0 | O120: =IF(M120="","",M120*Parâmetros!$C$5) -> 2584.9867 | P120: =IF(L120="","",IF(L120>=Parâmetros!$C$10,"Sim","Não"))
... A387: 385 | B387: 2492 | C387: Touro Bonsmara Descarte | D387: Bois Descarte | E387: 5 | F387: 46232 | G387: 301 | H387: =IF(COUNTIFS(Pesagens!$B$3:$B$5001,$B387)=0,"",_xlfn.MAXIFS(Pesagens!$A$3:$A$5001,Pesagens!$B$3:$B$5001,$B387,Pesagens!$E$3:$E$5001,"<>")) -> 46232 | I387: =IF($H387="","",IFERROR(AVERAGEIFS(Pesagens!$E$3:$E$5001,Pesagens!$B$3:$B$5001,$B387,Pesagens!$A$3:$A$5001,$H387),"")) -> 301 | J387: =IF(F387="","",Parâmetros!$C$4-F387) -> 14 | K387: =IF(OR(I387="",G387=""),"",I387-G387) -> 0 | L387: =IF(OR(I387="",G387="",H387<=F387),"",(I387-G387)/(H387-F387)) | M387: =IF(I387="","",I387*Parâmetros!$C$8/15) -> 10.635333 | N387: =IF(K387="","",K387*Parâmetros!$C$8/15) -> 0 | O387: =IF(M387="","",M387*Parâmetros!$C$5) -> 3296.9533 | P387: =IF(L387="","",IF(L387>=Parâmetros!$C$10,"Sim","Não"))

Sheet Pesagens
A1: HISTÓRICO DE PESAGENS
A2: Data | B2: Brinco | C2: Categoria | D2: Curral | E2: Peso (kg) | F2: Evento/Obs
A3: 46078 | B3: 2255 | C3: Touro Nelore | D3: 4-TN | E3: 374 | F3: Pesagem
A4: 46078 | B4: 2265 | C4: Touro Nelore | D4: 4-TN | E4: 367 | F4: Pesagem
A5: 46078 | B5: 2274 | C5: Touro Nelore | D5: 4-TN | E5: 388 | F5: Pesagem
A6: 46078 | B6: 2277 | C6: Touro Nelore | D6: 4-TN | E6: 381 | F6: Pesagem
A7: 46078 | B7: 2298 | C7: Touro Nelore | D7: 4-TN | E7: 383 | F7: Pesagem
A8: 46078 | B8: 2301 | C8: Touro Nelore | D8: 4-TN | E8: 379 | F8: Pesagem
A9: 46078 | B9: 2310 | C9: Touro Nelore | D9: 4-TN | E9: 427 | F9: Pesagem
A10: 46078 | B10: 2326 | C10: Touro Nelore | D10: 4-TN | E10: 384 | F10: Pesagem
A11: 46078 | B11: 2339 | C11: Touro Nelore | D11: 4-TN | E11: 374 | F11: Pesagem
A12: 46078 | B12: 2343 | C12: Touro Nelore | D12: 4-TN | E12: 401 | F12: Pesagem
A13: 46078 | B13: 2355 | C13: Touro Nelore | D13: 4-TN | E13: 369 | F13: Pesagem
A14: 46078 | B14: 2356 | C14: Touro Nelore | D14: 4-TN | E14: 423 | F14: Pesagem
... A681: 46232 | B681: 2301 | C681: Touro Nelore | D681: 4-TN | E681: 557 | F681: Entrada
A682: 46232 | B682: 2307 | C682: Touro Nelore | D682: 4-TN | E682: 577 | F682: Pesagem
A683: 46232 | B683: 2310 | C683: Touro Nelore | D683: 4-TN | E683: 564 | F683: Pesagem
A684: 46232 | B684: 2326 | C684: Touro Nelore | D684: 4-TN | E684: 538 | F684: Pesagem
A685: 46232 | B685: 2339 | C685: Touro Nelore | D685: 4-TN | E685: 514 | F685: Pesagem
A686: 46232 | B686: 2343 | C686: Touro Nelore | D686: 4-TN | E686: 573 | F686: Pesagem
A687: 46232 | B687: 2355 | C687: Touro Nelore | D687: 4-TN | E687: 531 | F687: Pesagem
A688: 46232 | B688: 2356 | C688: Touro Nelore | D688: 4-TN | E688: 539 | F688: Pesagem
A689: 46232 | B689: 2365 | C689: Touro Nelore | D689: 4-TN | E689: 504 | F689: Pesagem
A690: 46232 | B690: 2369 | C690: Touro Nelore | D690: 4-TN | E690: 580 | F690: Pesagem
A691: 46232 | B691: 2373 | C691: Touro Nelore | D691: 4-TN | E691: 545 | F691: Pesagem
A692: 46232 | B692: 2382 | C692: Touro Nelore | D692: 4-TN | E692: 536 | F692: Pesagem
A693: 46232 | B693: 2387 | C693: Touro Nelore | D693: 4-TN | E693: 517 | F693: Pesagem
A694: 46232 | B694: 2388 | C694: Touro Nelore | D694: 4-TN | E694: 512 | F694: Pesagem
... A719: 46246 | B719: 2339 | C719: Touro Nelore | D719: 4-TN | E719: 549 | F719: Venda/Abate - Frig Prima Foods (NF 137493)
A720: 46246 | B720: 2307 | C720: Touro Nelore | D720: 4-TN | E720: 610 | F720: Venda/Abate - Frig Prima Foods (NF 137493)
A721: 46246 | B721: 2431 | C721: Touro Nelore | D721: 4-TN | E721: 554 | F721: Venda/Abate - Frig Prima Foods (NF 137493)
A722: 46246 | B722: 2410 | C722: Touro Nelore | D722: 4-TN | E722: 491 | F722: Venda/Abate - Frig Prima Foods (NF 137493)
A723: 46246 | B723: 2373 | C723: Touro Nelore | D723: 4-TN | E723: 586 | F723: Venda/Abate - Frig Prima Foods (NF 137493)
A724: 46246 | B724: 2326 | C724: Touro Nelore | D724: 4-TN | E724: 562 | F724: Venda/Abate - Frig Prima Foods (NF 137493)
A725: 46246 | B725: 2301 | C725: Touro Nelore | D725: 4-TN | E725: 569 | F725: Venda/Abate - Frig Prima Foods (NF 137493)
A726: 46246 | B726: 2423 | C726: Touro Nelore | D726: 4-TN | E726: 592 | F726: Venda/Abate - Frig Prima Foods (NF 137493)
A727: 46246 | B727: 2403 | C727: Touro Nelore | D727: 4-TN | E727: 559 | F727: Venda/Abate - Frig Prima Foods (NF 137493)
A728: 46246 | B728: 2355 | C728: Touro Nelore | D728: 4-TN | E728: 565 | F728: Venda/Abate - Frig Prima Foods (NF 137493)
A729: 46246 | B729: 2369 | C729: Touro Nelore | D729: 4-TN | E729: 617 | F729: Venda/Abate - Frig Prima Foods (NF 137493)
A730: 46246 | B730: 2406 | C730: Touro Nelore | D730: 4-TN | E730: 530 | F730: Venda/Abate - Frig Prima Foods (NF 137493)
A731: 46246 | B731: 2432 | C731: Touro Nelore | D731: 4-TN | E731: 610 | F731: Venda/Abate - Frig Prima Foods (NF 137493)
A732: 46246 | B732: 2310 | C732: Touro Nelore | D732: 4-TN | E732: 588 | F732: Venda/Abate - Frig Prima Foods (NF 137493)
A733: 46246 | B733: 2365 | C733: Touro Nelore | D733: 4-TN | E733: 526 | F733: Venda/Abate - Frig Prima Foods (NF 137493)

Sheet Currais
A1: RESUMO POR CURRAL
A2: Curral | B2: Descrição | C2: Nº Cabeças | D2: Peso Médio Entrada (kg) | E2: Peso Médio Atual (kg) | F2: Peso Total Atual (kg) | G2: @ Total | H2: GMD Médio (kg/dia) | I2: Ganho Total (kg) | J2: Dieta | K2: Custo Dieta (R$/kg) | L2: % Silagem de Capim | M2: % Promill | N2: % Milho Moído | O2: % Ureia | P2: % Núcleo Flex
A3: 2 | B3: Touros Bonsmara — Retiro 1 | C3: =COUNTIFS(Cadastro_Animais!$E$3:$E$5001,A3) -> 38 | D3: =IFERROR(AVERAGEIFS(Cadastro_Animais!$G$3:$G$5001,Cadastro_Animais!$E$3:$E$5001,A3),"") -> 551.84211 | E3: =IFERROR(AVERAGEIFS(Cadastro_Animais!$I$3:$I$5001,Cadastro_Animais!$E$3:$E$5001,A3),"") -> 551.84211 | F3: =SUMIFS(Cadastro_Animais!$I$3:$I$5001,Cadastro_Animais!$E$3:$E$5001,A3) -> 20970 | G3: =F3*Parâmetros!$C$8/15 -> 740.94 | H3: =IFERROR(AVERAGEIFS(Cadastro_Animais!$L$3:$L$5001,Cadastro_Animais!$E$3:$E$5001,A3),"") | I3: =SUMIFS(Cadastro_Animais!$K$3:$K$5001,Cadastro_Animais!$E$3:$E$5001,A3) -> 0 | J3: Touros | K3: =IFERROR(INDEX(Ingredientes_Dieta!$E$11:$H$11,1,MATCH(J3,Ingredientes_Dieta!$E$5:$H$5,0)),"") -> 0.45771 | L3: =IFERROR(INDEX(Ingredientes_Dieta!$E$6:$H$10,MATCH("Silagem de Capim",Ingredientes_Dieta!$B$6:$B$10,0),MATCH($J3,Ingredientes_Dieta!$E$5:$H$5,0)),0) -> 0.68 | M3: =IFERROR(INDEX(Ingredientes_Dieta!$E$6:$H$10,MATCH("Promill",Ingredientes_Dieta!$B$6:$B$10,0),MATCH($J3,Ingredientes_Dieta!$E$5:$H$5,0)),0) -> 0.22 | N3: =IFERROR(INDEX(Ingredientes_Dieta!$E$6:$H$10,MATCH("Milho Moído",Ingredientes_Dieta!$B$6:$B$10,0),MATCH($J3,Ingredientes_Dieta!$E$5:$H$5,0)),0) -> 0.087 | O3: =IFERROR(INDEX(Ingredientes_Dieta!$E$6:$H$10,MATCH("Ureia",Ingredientes_Dieta!$B$6:$B$10,0),MATCH($J3,Ingredientes_Dieta!$E$5:$H$5,0)),0) -> 0.005 | P3: =IFERROR(INDEX(Ingredientes_Dieta!$E$6:$H$10,MATCH("Núcleo Flex (Flexbeef MD)",Ingredientes_Dieta!$B$6:$B$10,0),MATCH($J3,Ingredientes_Dieta!$E$5:$H$5,0)),0) -> 0.008
A4: 3 | B4: Touros Bonsmara — Retiro 2 | C4: =COUNTIFS(Cadastro_Animais!$E$3:$E$5001,A4) -> 46 | D4: =IFERROR(AVERAGEIFS(Cadastro_Animais!$G$3:$G$5001,Cadastro_Animais!$E$3:$E$5001,A4),"") -> 450.21739 | E4: =IFERROR(AVERAGEIFS(Cadastro_Animais!$I$3:$I$5001,Cadastro_Animais!$E$3:$E$5001,A4),"") -> 520.95652 | F4: =SUMIFS(Cadastro_Animais!$I$3:$I$5001,Cadastro_Animais!$E$3:$E$5001,A4) -> 23964 | G4: =F4*Parâmetros!$C$8/15 -> 846.728 | H4: =IFERROR(AVERAGEIFS(Cadastro_Animais!$L$3:$L$5001,Cadastro_Animais!$E$3:$E$5001,A4),"") -> 2.4392804 | I4: =SUMIFS(Cadastro_Animais!$K$3:$K$5001,Cadastro_Animais!$E$3:$E$5001,A4) -> 3254 | J4: Touros | K4: =IFERROR(INDEX(Ingredientes_Dieta!$E$11:$H$11,1,MATCH(J4,Ingredientes_Dieta!$E$5:$H$5,0)),"") -> 0.45771 | L4: =IFERROR(INDEX(Ingredientes_Dieta!$E$6:$H$10,MATCH("Silagem de Capim",Ingredientes_Dieta!$B$6:$B$10,0),MATCH($J4,Ingredientes_Dieta!$E$5:$H$5,0)),0) -> 0.68 | M4: =IFERROR(INDEX(Ingredientes_Dieta!$E$6:$H$10,MATCH("Promill",Ingredientes_Dieta!$B$6:$B$10,0),MATCH($J4,Ingredientes_Dieta!$E$5:$H$5,0)),0) -> 0.22 | N4: =IFERROR(INDEX(Ingredientes_Dieta!$E$6:$H$10,MATCH("Milho Moído",Ingredientes_Dieta!$B$6:$B$10,0),MATCH($J4,Ingredientes_Dieta!$E$5:$H$5,0)),0) -> 0.087 | O4: =IFERROR(INDEX(Ingredientes_Dieta!$E$6:$H$10,MATCH("Ureia",Ingredientes_Dieta!$B$6:$B$10,0),MATCH($J4,Ingredientes_Dieta!$E$5:$H$5,0)),0) -> 0.005 | P4: =IFERROR(INDEX(Ingredientes_Dieta!$E$6:$H$10,MATCH("Núcleo Flex (Flexbeef MD)",Ingredientes_Dieta!$B$6:$B$10,0),MATCH($J4,Ingredientes_Dieta!$E$5:$H$5,0)),0) -> 0.008
A5: 4 | B5: Bezerros — Confinamento | C5: =COUNTIFS(Cadastro_Animais!$E$3:$E$5001,A5) -> 165 | D5: =IFERROR(AVERAGEIFS(Cadastro_Animais!$G$3:$G$5001,Cadastro_Animais!$E$3:$E$5001,A5),"") -> 219.67879 | E5: =IFERROR(AVERAGEIFS(Cadastro_Animais!$I$3:$I$5001,Cadastro_Animais!$E$3:$E$5001,A5),"") -> 219.67879 | F5: =SUMIFS(Cadastro_Animais!$I$3:$I$5001,Cadastro_Animais!$E$3:$E$5001,A5) -> 36247 | G5: =F5*Parâmetros!$C$8/15 -> 1280.7273 | H5: =IFERROR(AVERAGEIFS(Cadastro_Animais!$L$3:$L$5001,Cadastro_Animais!$E$3:$E$5001,A5),"") | I5: =SUMIFS(Cadastro_Animais!$K$3:$K$5001,Cadastro_Animais!$E$3:$E$5001,A5) -> 0 | J5: Bezerros | K5: =IFERROR(INDEX(Ingredientes_Dieta!$E$11:$H$11,1,MATCH(J5,Ingredientes_Dieta!$E$5:$H$5,0)),"") -> 0.52245 | L5: =IFERROR(INDEX(Ingredientes_Dieta!$E$6:$H$10,MATCH("Silagem de Capim",Ingredientes_Dieta!$B$6:$B$10,0),MATCH($J5,Ingredientes_Dieta!$E$5:$H$5,0)),0) -> 0.62 | M5: =IFERROR(INDEX(Ingredientes_Dieta!$E$6:$H$10,MATCH("Promill",Ingredientes_Dieta!$B$6:$B$10,0),MATCH($J5,Ingredientes_Dieta!$E$5:$H$5,0)),0) -> 0.3 | N5: =IFERROR(INDEX(Ingredientes_Dieta!$E$6:$H$10,MATCH("Milho Moído",Ingredientes_Dieta!$B$6:$B$10,0),MATCH($J5,Ingredientes_Dieta!$E$5:$H$5,0)),0) -> 0.065 | O5: =IFERROR(INDEX(Ingredientes_Dieta!$E$6:$H$10,MATCH("Ureia",Ingredientes_Dieta!$B$6:$B$10,0),MATCH($J5,Ingredientes_Dieta!$E$5:$H$5,0)),0) -> 0.005 | P5: =IFERROR(INDEX(Ingredientes_Dieta!$E$6:$H$10,MATCH("Núcleo Flex (Flexbeef MD)",Ingredientes_Dieta!$B$6:$B$10,0),MATCH($J5,Ingredientes_Dieta!$E$5:$H$5,0)),0) -> 0.01
A6: 4-TN | B6: Touros Nelore | C6: =COUNTIFS(Cadastro_Animais!$E$3:$E$5001,A6) -> 29 | D6: =IFERROR(AVERAGEIFS(Cadastro_Animais!$G$3:$G$5001,Cadastro_Animais!$E$3:$E$5001,A6),"") -> 464.2069 | E6: =IFERROR(AVERAGEIFS(Cadastro_Animais!$I$3:$I$5001,Cadastro_Animais!$E$3:$E$5001,A6),"") -> 558.72414 | F6: =SUMIFS(Cadastro_Animais!$I$3:$I$5001,Cadastro_Animais!$E$3:$E$5001,A6) -> 16203 | G6: =F6*Parâmetros!$C$8/15 -> 572.506 | H6: =IFERROR(AVERAGEIFS(Cadastro_Animais!$L$3:$L$5001,Cadastro_Animais!$E$3:$E$5001,A6),"") -> 2.259145 | I6: =SUMIFS(Cadastro_Animais!$K$3:$K$5001,Cadastro_Animais!$E$3:$E$5001,A6) -> 2741 | J6: Boi Nelore | K6: =IFERROR(INDEX(Ingredientes_Dieta!$E$11:$H$11,1,MATCH(J6,Ingredientes_Dieta!$E$5:$H$5,0)),"") -> 0.66905 | L6: =IFERROR(INDEX(Ingredientes_Dieta!$E$6:$H$10,MATCH("Silagem de Capim",Ingredientes_Dieta!$B$6:$B$10,0),MATCH($J6,Ingredientes_Dieta!$E$5:$H$5,0)),0) -> 0.48 | M6: =IFERROR(INDEX(Ingredientes_Dieta!$E$6:$H$10,MATCH("Promill",Ingredientes_Dieta!$B$6:$B$10,0),MATCH($J6,Ingredientes_Dieta!$E$5:$H$5,0)),0) -> 0.22 | N6: =IFERROR(INDEX(Ingredientes_Dieta!$E$6:$H$10,MATCH("Milho Moído",Ingredientes_Dieta!$B$6:$B$10,0),MATCH($J6,Ingredientes_Dieta!$E$5:$H$5,0)),0) -> 0.285 | O6: =IFERROR(INDEX(Ingredientes_Dieta!$E$6:$H$10,MATCH("Ureia",Ingredientes_Dieta!$B$6:$B$10,0),MATCH($J6,Ingredientes_Dieta!$E$5:$H$5,0)),0) -> 0.005 | P6: =IFERROR(INDEX(Ingredientes_Dieta!$E$6:$H$10,MATCH("Núcleo Flex (Flexbeef MD)",Ingredientes_Dieta!$B$6:$B$10,0),MATCH($J6,Ingredientes_Dieta!$E$5:$H$5,0)),0) -> 0.01
A7: (a definir) | B7: Novilhas Nelore | C7: =COUNTIFS(Cadastro_Animais!$E$3:$E$5001,A7) -> 70 | D7: =IFERROR(AVERAGEIFS(Cadastro_Animais!$G$3:$G$5001,Cadastro_Animais!$E$3:$E$5001,A7),"") -> 342.02857 | E7: =IFERROR(AVERAGEIFS(Cadastro_Animais!$I$3:$I$5001,Cadastro_Animais!$E$3:$E$5001,A7),"") -> 342.02857 | F7: =SUMIFS(Cadastro_Animais!$I$3:$I$5001,Cadastro_Animais!$E$3:$E$5001,A7) -> 23942 | G7: =F7*Parâmetros!$C$8/15 -> 845.95067 | H7: =IFERROR(AVERAGEIFS(Cadastro_Animais!$L$3:$L$5001,Cadastro_Animais!$E$3:$E$5001,A7),"") | I7: =SUMIFS(Cadastro_Animais!$K$3:$K$5001,Cadastro_Animais!$E$3:$E$5001,A7) -> 0 | J7: Boi Nelore | K7: =IFERROR(INDEX(Ingredientes_Dieta!$E$11:$H$11,1,MATCH(J7,Ingredientes_Dieta!$E$5:$H$5,0)),"") -> 0.66905 | L7: =IFERROR(INDEX(Ingredientes_Dieta!$E$6:$H$10,MATCH("Silagem de Capim",Ingredientes_Dieta!$B$6:$B$10,0),MATCH($J7,Ingredientes_Dieta!$E$5:$H$5,0)),0) -> 0.48 | M7: =IFERROR(INDEX(Ingredientes_Dieta!$E$6:$H$10,MATCH("Promill",Ingredientes_Dieta!$B$6:$B$10,0),MATCH($J7,Ingredientes_Dieta!$E$5:$H$5,0)),0) -> 0.22 | N7: =IFERROR(INDEX(Ingredientes_Dieta!$E$6:$H$10,MATCH("Milho Moído",Ingredientes_Dieta!$B$6:$B$10,0),MATCH($J7,Ingredientes_Dieta!$E$5:$H$5,0)),0) -> 0.285 | O7: =IFERROR(INDEX(Ingredientes_Dieta!$E$6:$H$10,MATCH("Ureia",Ingredientes_Dieta!$B$6:$B$10,0),MATCH($J7,Ingredientes_Dieta!$E$5:$H$5,0)),0) -> 0.005 | P7: =IFERROR(INDEX(Ingredientes_Dieta!$E$6:$H$10,MATCH("Núcleo Flex (Flexbeef MD)",Ingredientes_Dieta!$B$6:$B$10,0),MATCH($J7,Ingredientes_Dieta!$E$5:$H$5,0)),0) -> 0.01
A8: 5 | B8: Touros Bonsmara Descarte | C8: =COUNTIFS(Cadastro_Animais!$E$3:$E$5001,A8) -> 37 | D8: =IFERROR(AVERAGEIFS(Cadastro_Animais!$G$3:$G$5001,Cadastro_Animais!$E$3:$E$5001,A8),"") -> 351.48649 | E8: =IFERROR(AVERAGEIFS(Cadastro_Animais!$I$3:$I$5001,Cadastro_Animais!$E$3:$E$5001,A8),"") -> 351.48649 | F8: =SUMIFS(Cadastro_Animais!$I$3:$I$5001,Cadastro_Animais!$E$3:$E$5001,A8) -> 13005 | G8: =F8*Parâmetros!$C$8/15 -> 459.51 | H8: =IFERROR(AVERAGEIFS(Cadastro_Animais!$L$3:$L$5001,Cadastro_Animais!$E$3:$E$5001,A8),"") | I8: =SUMIFS(Cadastro_Animais!$K$3:$K$5001,Cadastro_Animais!$E$3:$E$5001,A8) -> 0 | J8: Descarte | K8: =IFERROR(INDEX(Ingredientes_Dieta!$E$11:$H$11,1,MATCH(J8,Ingredientes_Dieta!$E$5:$H$5,0)),"") -> 0.57515 | L8: =IFERROR(INDEX(Ingredientes_Dieta!$E$6:$H$10,MATCH("Silagem de Capim",Ingredientes_Dieta!$B$6:$B$10,0),MATCH($J8,Ingredientes_Dieta!$E$5:$H$5,0)),0) -> 0.57 | M8: =IFERROR(INDEX(Ingredientes_Dieta!$E$6:$H$10,MATCH("Promill",Ingredientes_Dieta!$B$6:$B$10,0),MATCH($J8,Ingredientes_Dieta!$E$5:$H$5,0)),0) -> 0.26 | N8: =IFERROR(INDEX(Ingredientes_Dieta!$E$6:$H$10,MATCH("Milho Moído",Ingredientes_Dieta!$B$6:$B$10,0),MATCH($J8,Ingredientes_Dieta!$E$5:$H$5,0)),0) -> 0.155 | O8: =IFERROR(INDEX(Ingredientes_Dieta!$E$6:$H$10,MATCH("Ureia",Ingredientes_Dieta!$B$6:$B$10,0),MATCH($J8,Ingredientes_Dieta!$E$5:$H$5,0)),0) -> 0.005 | P8: =IFERROR(INDEX(Ingredientes_Dieta!$E$6:$H$10,MATCH("Núcleo Flex (Flexbeef MD)",Ingredientes_Dieta!$B$6:$B$10,0),MATCH($J8,Ingredientes_Dieta!$E$5:$H$5,0)),0) -> 0.01
B9: TOTAL | C9: =SUM(C3:C8) -> 385 | F9: =SUM(F3:F8) -> 134331 | G9: =SUM(G3:G8) -> 4746.362 | I9: =SUM(I3:I8) -> 5995
